Workbook

Sheet raw_data(dont change)
A1: Order ID | B1: Order Date | C1: Customer ID | D1: Type | E1: SKU | F1: Category | G1: Product Name | H1: Unit Price | I1: Qty | J1: Total | K1: Discount Code | L1: Disc % | M1: Payment | N1: Source | O1: City | P1: State | Q1: Warehouse | R1: Del Date | S1: Status | T1: Return? | U1: Reason | V1: Ret Rec | W1: Refund
A2: UT-100001 | B2: 2024-10-01 | C2: CUST_10001 | D2: New | E2: TOP-CAS-M | F2: Tops | G2: Classic Cotton Tee | H2: 1299 | I2: 2 | J2: 2598 | L2: 0 | M2: UPI | N2: Website | O2: Mumbai | P2: Maharashtra | Q2: Mumbai | R2: 2024-10-05 | S2: Delivered | T2: No | W2: Not Applicable
A3: UT-100002 | B3: 2024-10-01 | C3: CUST_10002 | D3: Returning | E3: DRS-FRM-S | F3: Dresses | G3: Floral Midi Dress | H3: 2499 | I3: 1 | J3: 2499 | K3: DIWALI20 | L3: 20 | M3: Credit Card | N3: Mobile App | O3: Delhi | P3: Delhi | Q3: Delhi | R3: 2024-10-04 | S3: Delivered | T3: Yes | U3: Size Issue | V3: 2024-10-15 | W3: Processed
A4: UT-100003 | B4: 2024-01-10 | C4: CUST_10003 | D4: new | E4: BOT-JNS-L | F4: Bottoms | G4: Slim Fit Jeans | H4: 1899 | I4: 1 | J4: 1899 | L4: 0 | M4: COD | N4: Website | O4: Bangalore | P4: Karnataka | Q4: Bangalore | R4: 2024-10-06 | S4: Delivered | T4: No | W4: Not Applicable
A5: UT-100004 | B5: 2024-10-01 | C5: CUST_10004 | D5: New | E5: OUT-JKT-XL | F5: Outerwear | G5: Denim Jacket | H5: 3499 | I5: 1 | J5: 3499 | K5: FIRST15 | L5: 15 | M5: Debit Card | N5: Instagram Shop | O5: Chennai | P5: Tamil Nadu | Q5: Mumbai | R5: 2024-10-08 | S5: Delivered | T5: Yes | U5: Quality Defect | V5: 2024-10-20 | W5: Processed
A6: UT-100005 | B6: 2024-10-01 | C6: CUST_10001 | D6: New | E6: ACC-SCF-OS | F6: Accessories | G6: Silk Scarf | H6: 799 | I6: 3 | J6: 2397 | L6: 0 | M6: UPI | N6: Website | O6: Mumbai | P6: Maharashtra | Q6: Mumbai | R6: 2024-10-06 | S6: Delivered | T6: No | W6: Not Applicable
A7: UT-100006 | B7: 2024-10-02 | C7: CUST_10005 | D7: Returning | E7: TOP-FRM-S | F7: Tops | G7: Printed Blouse | H7: 1599 | I7: 2 | J7: 3198 | L7: 0 | M7: Credit Card | N7: Mobile App | O7: Hyderabad | P7: Telangana | Q7: Bangalore | R7: 2024-10-07 | S7: Delivered | T7: Yes | U7: Changed Mind | V7: 2024-10-18 | W7: Processed
A8: UT-100007 | B8: 2024-10-02 | C8: CUST_10006 | D8: New | E8: DRS-CAS-M | F8: Dresses | G8: A-Line Dress | H8: 2199 | I8: 1 | J8: 2199 | K8: DIWALI20 | L8: 20 | M8: COD | N8: Website | O8: Pune | P8: Maharashtra | Q8: Mumbai | S8: Cancelled | T8: No | W8: Not Applicable
A9: UT-100008 | B9: 2024-10-02 | C9: CUST_10007 | D9: New | E9: BOT-TRS-L | F9: Bottoms | G9: Formal Trousers | H9: 2299 | I9: 1 | J9: 2299 | L9: 0 | M9: UPI | N9: Mobile App | O9: Kolkata | P9: West Bengal | Q9: Delhi | R9: 2024-10-10 | S9: Delivered | T9: No | W9: Not Applicable
A10: UT-100009 | B10: 2024-10-02 | C10: CUST_10008 | D10: Returning | E10: TOP-CAS-XL | F10: Tops | G10: Oversized Tee | H10: 1399 | I10: 5 | J10: 6995 | L10: 0 | M10: Credit Card | N10: Website | O10: Ahmedabad | P10: Gujarat | Q10: Mumbai | R10: 2024-10-09 | S10: Delivered | T10: Yes | U10: Size Issue | V10: 2024-10-22 | W10: Processed
A11: UT-100010 | B11: 2024-10-02 | C11: CUST_10009 | D11: New | E11: OUT-BLZ-M | F11: Outerwear | G11: Casual Blazer | H11: 4999 | I11: -1 | J11: 4999 | L11: 0 | M11: Debit Card | N11: Instagram Shop | O11: Jaipur | P11: Rajasthan | Q11: Delhi | R11: 2024-10-11 | S11: Delivered | T11: Yes | U11: Wrong Item | V11: 2024-10-25 | W11: Pending
A12: UT-100011 | B12: 2024-10-03 | C12: CUST_10010 | D12: New | E12: ACC-BAG-OS | F12: Accessories | G12: Tote Bag | H12: 1299 | I12: 2 | J12: 2598 | K12: FLAT10 | L12: 10 | M12: Wallet | N12: Website | O12: Lucknow | P12: Uttar Pradesh | Q12: Delhi | R12: 2024-10-10 | S12: Delivered | T12: No | W12: Not Applicable
A13: UT-100012 | B13: 2024-10-03 | C13: CUST_10011 | D13: New | E13: DRS-PRT-S | F13: Dresses | G13: Party Dress | H13: 3299 | I13: 1 | J13: 3299 | L13: 0 | M13: COD | N13: Mobile App | O13: Chandigarh | P13: Punjab | Q13: Delhi | S13: RTO | T13: No | W13: Not Applicable
A14: UT-100013 | B14: 2024-10-03 | C14: CUST_10012 | D14: Returning | E14: TOP-SLK-M | F14: Tops | G14: Silk Blouse | H14: 2499 | I14: 1 | J14: 2499 | L14: 0 | M14: Credit Card | N14: Website | O14: Mumbai | P14: Maharashtra | Q14: Mumbai | R14: 2024-10-09 | S14: Delivered | T14: No | W14: Not Applicable
A15: UT-100014 | B15: 2024-10-03 | C15: CUST_10013 | D15: New | E15: BOT-SKT-S | F15: Bottoms | G15: Pleated Skirt | H15: 1799 | I15: 2 | J15: 3598 | K15: DIWALI20 | L15: 20 | M15: UPI | N15: Instagram Shop | O15: Delhi | P15: Delhi | Q15: Delhi | R15: 2024-10-11 | S15: Delivered | T15: Yes | U15: Size Issue | V15: 2024-10-28 | W15: Processed
A16: UT-100015 | B16: 2024-10-03 | C16: CUST_10014 | D16: New | E16: OUT-CRD-L | F16: Outerwear | G16: Knit Cardigan | H16: 2799 | I16: 1 | J16: 2799 | L16: 0 | M16: Debit Card | N16: Mobile App | O16: Bangalore | P16: Karnataka | Q16: Bangalore | R16: 2024-10-12 | S16: Delivered | T16: No | W16: Not Applicable
A17: UT-100016 | B17: 2024-10-04 | C17: CUST_10015 | D17: Returning | E17: ACC-JWL-OS | F17: Accessories | G17: Statement Earrings | H17: 599 | I17: 4 | J17: 2396 | L17: 0 | M17: COD | N17: Website | O17: Noida | P17: Uttar Pradesh | Q17: Delhi | R17: 2024-10-14 | S17: Delivered | T17: Yes | U17: Damaged in Transit | V17: 2024-10-26 | W17: Processed
A18: UT-100017 | B18: 2024-10-04 | C18: CUST_10016 | D18: New | E18: TOP-CRP-XS | F18: Tops | G18: Crop Top | H18: 999 | I18: 1 | J18: 999 | K18: FIRST15 | L18: 15 | M18: UPI | N18: Mobile App | O18: Gurgaon | P18: Haryana | Q18: Delhi | R18: 2024-10-12 | S18: Delievered | T18: No | W18: Not Applicable
A19: UT-100018 | B19: 2024-10-04 | C19: CUST_10017 | D19: New | E19: DRS-MAX-M | F19: Dresses | G19: Maxi Dress | H19: 2899 | I19: 1 | J19: 2899 | L19: 0 | M19: Credit Card | N19: Website | O19: Indore | P19: Madhya Pradesh | Q19: Mumbai | R19: 2024-10-14 | S19: Delivered | T19: No | W19: Not Applicable
A20: UT-100019 | B20: 2024-10-04 | C20: CUST_10018 | D20: Returning | E20: BOT-JGR-M | F20: Bottoms | G20: Joggers | H20: 1499 | I20: 2 | J20: 2998 | L20: 0 | M20: Wallet | N20: Instagram Shop | O20: Surat | P20: Gujarat | Q20: Mumbai | R20: 2024-10-13 | S20: Delivered | T20: Yes | U20: Size Issue | V20: 2024-10-30 | W20: Processed
A21: UT-100020 | B21: 2024-10-05 | C21: CUST_10019 | D21: New | E21: OUT-VST-S | F21: Outerwear | G21: Puffer Vest | H21: 3999 | I21: 1 | J21: 3999 | K21: DIWALI20 | L21: 20 | M21: COD | N21: Website | O21: Patna | P21: Bihar | Q21: Delhi | S21: RTO | T21: No | W21: Not Applicable
A22: UT-100021 | B22: 2024-10-05 | C22: CUST_10020 | D22: New | E22: TOP-TUN-L | F22: Tops | G22: Tunic Top | H22: 1699 | I22: 1 | J22: 1699 | L22: 0 | M22: UPI | N22: Mobile App | O22: Bhopal | P22: Madhya Pradesh | Q22: Mumbai | R22: 2024-10-15 | S22: Delivered | T22: No | W22: Not Applicable
A23: UT-100022 | B23: 2024-10-05 | C23: CUST_10021 | D23: Returning | E23: DRS-SHT-XS | F23: Dresses | G23: Shirt Dress | H23: 2399 | I23: 1 | J23: 2399 | L23: 0 | M23: Credit Card | N23: Website | O23: Nagpur | P23: Maharashtra | Q23: Mumbai | R23: 2024-10-16 | S23: Delivered | T23: Yes | U23: Quality Defect | V23: 2024-11-02 | W23: Processed
A24: UT-100023 | B24: 2024-10-05 | C24: CUST_10022 | D24: New | E24: ACC-BLT-M | F24: Accessories | G24: Leather Belt | H24: 899 | I24: 1 | J24: 899 | K24: FLAT10 | L24: 10 | M24: Debit Card | N24: Mobile App | O24: Coimbatore | P24: Tamil Nadu | Q24: Bangalore | R24: 2024-10-17 | S24: Delivered | T24: No | W24: Not Applicable
A25: UT-100024 | B25: 2024-10-06 | C25: CUST_10023 | D25: New | E25: BOT-SHT-M | F25: Bottoms | G25: Cotton Shorts | H25: 1199 | I25: 3 | J25: 3597 | L25: 0 | M25: COD | N25: Instagram Shop | O25: Kochi | P25: Kerala | Q25: Bangalore | R25: 2024-10-18 | S25: Delivered | T25: Yes | U25: Changed Mind | V25: 2024-11-05 | W25: Processed
A26: UT-100025 | B26: 2024-10-06 | C26: CUST_10024 | D26: New | E26: TOP-PLO-L | F26: Tops | G26: Polo Shirt | H26: 1799 | I26: 2 | J26: 3598 | L26: 0 | M26: UPI | N26: Website | O26: Vizag | P26: Andhra Pradesh | Q26: Bangalore | R26: 2024-10-17 | S26: Delivered | T26: No | W26: Not Applicable
A27: UT-100026 | B27: 2024-10-06 | C27: CUST_10025 | D27: New | E27: DRS-WRK-M | F27: Dresses | G27: Work Dress | H27: 2699 | I27: 1 | J27: 2699 | L27: 0 | M27: Credit Card | N27: Mobile App | O27: Thiruvananthapuram | P27: Kerala | Q27: Bangalore | R27: 2024-10-18 | S27: Delivered | T27: No | W27: Not Applicable
A28: UT-100027 | B28: 2024-10-06 | C28: CUST_10026 | D28: Returning | E28: OUT-TRN-L | F28: Outerwear | G28: Trench Coat | H28: 4599 | I28: 1 | J28: 4599 | K28: FLAT10 | L28: 10 | M28: Debit Card | N28: Website | O28: Mysore | P28: Karnataka | Q28: Bangalore | R28: 2024-10-19 | S28: Delivered | T28: Yes | U28: Size Issue | V28: 2024-11-08 | W28: Processed
A29: UT-100028 | B29: 2024-10-07 | C29: CUST_10027 | D29: New | E29: ACC-HAT-OS | F29: Accessories | G29: Fedora Hat | H29: 1099 | I29: 1 | J29: 1099 | L29: 0 | M29: UPI | N29: Instagram Shop | O29: Vadodara | P29: Gujarat | Q29: Mumbai | R29: 2024-10-20 | S29: Delivered | T29: No | W29: Not Applicable
A30: UT-100029 | B30: 2024-10-07 | C30: CUST_10028 | D30: New | E30: TOP-DNM-M | F30: Tops | G30: Denim Shirt | H30: 1899 | I30: 1 | J30: 1899 | L30: 0 | M30: COD | N30: Mobile App | O30: Rajkot | P30: Gujarat | Q30: Mumbai | S30: RTO | T30: No | W30: Not Applicable
A31: UT-100030 | B31: 2024-10-07 | C31: CUST_10029 | D31: New | E31: BOT-CRG-L | F31: Bottoms | G31: Cargo Pants | H31: 2199 | I31: 1 | J31: 2199 | K31: DIWALI20 | L31: 20 | M31: Credit Card | N31: Website | O31: Kanpur | P31: Uttar Pradesh | Q31: Delhi | R31: 2024-10-20 | S31: Delivered | T31: No | W31: Not Applicable
A32: UT-100031 | B32: 2024-10-07 | C32: CUST_10030 | D32: Returning | E32: DRS-EVE-S | F32: Dresses | G32: Evening Gown | H32: 5499 | I32: 1 | J32: 5499 | L32: 0 | M32: Credit Card | N32: Mobile App | O32: Mumbai | P32: Maharashtra | Q32: Mumbai | R32: 2024-10-21 | S32: Delivered | T32: Yes | U32: Size Issue | V32: 2024-11-10 | W32: Processed
A33: UT-100032 | B33: 2024-10-08 | C33: CUST_10031 | D33: New | E33: TOP-BAS-M | F33: Tops | G33: Basic Tank | H33: 899 | I33: 2 | J33: 1798 | L33: 0 | M33: UPI | N33: Website | O33: Delhi | P33: Delhi | Q33: Delhi | R33: 2024-10-14 | S33: Delivered | T33: No | W33: Not Applicable
A34: UT-100033 | B34: 2024-10-08 | C34: CUST_10032 | D34: New | E34: OUT-WOL-L | F34: Outerwear | G34: Wool Coat | H34: 6999 | I34: 1 | J34: 6999 | K34: FIRST15 | L34: 15 | M34: Debit Card | N34: Instagram Shop | O34: Kolkata | P34: West Bengal | Q34: Delhi | R34: 2024-10-16 | S34: Delivered | T34: Yes | U34: Quality Defect | V34: 2024-11-05 | W34: Processed
A35: UT-100034 | B35: 2024-10-08 | C35: CUST_10033 | D35: Returning | E35: ACC-WCH-OS | F35: Accessories | G35: Fashion Watch | H35: 2999 | I35: 1 | J35: 2999 | L35: 0 | M35: Credit Card | N35: Mobile App | O35: Chennai | P35: Tamil Nadu | Q35: Bangalore | R35: 2024-10-15 | S35: Delivered | T35: No | W35: Not Applicable
A36: UT-100035 | B36: 2024-10-08 | C36: CUST_10034 | D36: New | E36: BOT-DNM-S | F36: Bottoms | G36: Denim Shorts | H36: 1599 | I36: 1 | J36: 1599 | L36: 0 | M36: COD | N36: Website | O36: Hyderabad | P36: Telangana | Q36: Bangalore | R36: 2024-10-17 | S36: Delivered | T36: Yes | U36: Size Issue | V36: 2024-11-08 | W36: Processed
A37: UT-100036 | B37: 2024-10-09 | C37: CUST_10035 | D37: New | E37: DRS-SUN-M | F37: Dresses | G37: Sundress | H37: 1999 | I37: 1 | J37: 1999 | K37: DIWALI20 | L37: 20 | M37: Wallet | N37: Mobile App | O37: Pune | P37: Maharashtra | Q37: Mumbai | R37: 2024-10-16 | S37: Delivered | T37: No | W37: Not Applicable
A38: UT-100037 | B38: 2024-10-09 | C38: CUST_10036 | D38: New | E38: TOP-RFL-S | F38: Tops | G38: Ruffle Top | H38: 1799 | I38: 1 | J38: 1799 | L38: 0 | M38: UPI | N38: Instagram Shop | O38: Ahmedabad | P38: Gujarat | Q38: Mumbai | R38: 2024-10-17 | S38: Delivered | T38: Yes | U38: Changed Mind | V38: 2024-11-12 | W38: Processed
A39: UT-100038 | B39: 2024-10-09 | C39: CUST_10037 | D39: Returning | E39: OUT-LTH-M | F39: Outerwear | G39: Leather Jacket | H39: 7999 | I39: 1 | J39: 7999 | L39: 0 | M39: Credit Card | N39: Website | O39: Jaipur | P39: Rajasthan | Q39: Delhi | R39: 2024-10-18 | S39: Delivered | T39: No | W39: Not Applicable
A40: UT-100039 | B40: 2024-10-09 | C40: CUST_10038 | D40: New | E40: ACC-SNG-OS | F40: Accessories | G40: Sunglasses | H40: 1499 | I40: 1 | J40: 1499 | K40: FLAT10 | L40: 10 | M40: Debit Card | N40: Mobile App | O40: Lucknow | P40: Uttar Pradesh | Q40: Delhi | R40: 2024-10-17 | S40: Delivered | T40: No | W40: Not Applicable
A41: UT-100040 | B41: 2024-10-10 | C41: CUST_10039 | D41: New | E41: BOT-PLZ-L | F41: Bottoms | G41: Palazzo Pants | H41: 1699 | I41: 1 | J41: 1699 | L41: 0 | M41: COD | N41: Website | O41: Bangalore | P41: Karnataka | Q41: Bangalore | R41: 2024-10-19 | S41: Delivered | T41: Yes | U41: Size Issue | V41: 2024-11-10 | W41: Processed
A42: UT-100041 | B42: 2024-10-10 | C42: CUST_10040 | D42: New | E42: DRS-BDC-S | F42: Dresses | G42: Bodycon Dress | H42: 2299 | I42: 1 | J42: 2299 | L42: 0 | M42: UPI | N42: Instagram Shop | O42: Mumbai | P42: Maharashtra | Q42: Mumbai | R42: 2024-10-18 | S42: Delivered | T42: No | W42: Not Applicable
A43: UT-100042 | B43: 2024-10-10 | C43: CUST_10041 | D43: Returning | E43: TOP-OFF-M | F43: Tops | G43: Off-Shoulder Top | H43: 1599 | I43: 2 | J43: 3198 | K43: DIWALI20 | L43: 20 | M43: Credit Card | N43: Mobile App | O43: Delhi | P43: Delhi | Q43: Delhi | R43: 2024-10-17 | S43: Delivered | T43: Yes | U43: Wrong Item | V43: 2024-11-08 | W43: Processed
A44: UT-100043 | B44: 2024-10-10 | C44: CUST_10042 | D44: New | E44: OUT-DNM-L | F44: Outerwear | G44: Denim Vest | H44: 2499 | I44: 1 | J44: 2499 | L44: 0 | M44: Wallet | N44: Website | O44: Chandigarh | P44: Punjab | Q44: Delhi | R44: 2024-10-20 | S44: Delivered | T44: No | W44: Not Applicable
A45: UT-100044 | B45: 2024-10-11 | C45: CUST_10043 | D45: New | E45: ACC-HBG-OS | F45: Accessories | G45: Hobo Bag | H45: 1899 | I45: 1 | J45: 1899 | L45: 0 | M45: Debit Card | N45: Instagram Shop | O45: Noida | P45: Uttar Pradesh | Q45: Delhi | R45: 2024-10-21 | S45: Delivered | T45: Yes | U45: Damaged in Transit | V45: 2024-11-12 | W45: Processed
A46: UT-100045 | B46: 2024-10-11 | C46: CUST_10044 | D46: New | E46: BOT-CHP-M | F46: Bottoms | G46: Chino Pants | H46: 1999 | I46: 1 | J46: 1999 | K46: FIRST15 | L46: 15 | M46: UPI | N46: Mobile App | O46: Gurgaon | P46: Haryana | Q46: Delhi | R46: 2024-10-19 | S46: Delivered | T46: No | W46: Not Applicable
A47: UT-100046 | B47: 2024-10-11 | C47: CUST_10045 | D47: Returning | E47: DRS-WRP-M | F47: Dresses | G47: Wrap Dress | H47: 2599 | I47: 1 | J47: 2599 | L47: 0 | M47: Credit Card | N47: Website | O47: Indore | P47: Madhya Pradesh | Q47: Mumbai | R47: 2024-10-20 | S47: Delivered | T47: No | W47: Not Applicable
A48: UT-100047 | B48: 2024-10-11 | C48: CUST_10046 | D48: New | E48: TOP-STR-S | F48: Tops | G48: Striped Tee | H48: 1299 | I48: 1 | J48: 1299 | L48: 0 | M48: COD | N48: Instagram Shop | O48: Surat | P48: Gujarat | Q48: Mumbai | S48: RTO | T48: No | W48: Not Applicable
A49: UT-100048 | B49: 2024-10-12 | C49: CUST_10047 | D49: New | E49: OUT-PRK-XL | F49: Outerwear | G49: Parka Jacket | H49: 5999 | I49: 1 | J49: 5999 | K49: DIWALI20 | L49: 20 | M49: Credit Card | N49: Mobile App | O49: Patna | P49: Bihar | Q49: Delhi | R49: 2024-10-22 | S49: Delivered | T49: Yes | U49: Size Issue | V49: 2024-11-15 | W49: Processed
A50: UT-100049 | B50: 2024-10-12 | C50: CUST_10048 | D50: New | E50: ACC-EAR-OS | F50: Accessories | G50: Hoop Earrings | H50: 799 | I50: 2 | J50: 1598 | L50: 0 | M50: UPI | N50: Website | O50: Bhopal | P50: Madhya Pradesh | Q50: Mumbai | R50: 2024-10-20 | S50: Delivered | T50: No | W50: Not Applicable
A51: UT-100050 | B51: 2024-10-12 | C51: CUST_10049 | D51: Returning | E51: BOT-LGN-S | F51: Bottoms | G51: Leggings | H51: 999 | I51: 2 | J51: 1998 | L51: 0 | M51: Wallet | N51: Mobile App | O51: Nagpur | P51: Maharashtra | Q51: Mumbai | R51: 2024-10-19 | S51: Delivered | T51: No | W51: Not Applicable
A52: UT-100051 | B52: 2024-10-12 | C52: CUST_10050 | D52: New | E52: DRS-CTN-L | F52: Dresses | G52: Cotton Dress | H52: 1899 | I52: 1 | J52: 1899 | L52: 0 | M52: Debit Card | N52: Instagram Shop | O52: Coimbatore | P52: Tamil Nadu | Q52: Bangalore | R52: 2024-10-22 | S52: Delivered | T52: Yes | U52: Quality Defect | V52: 2024-11-14 | W52: Processed
A53: UT-100052 | B53: 2024-10-13 | C53: CUST_10051 | D53: New | E53: TOP-LCE-M | F53: Tops | G53: Lace Top | H53: 1699 | I53: 1 | J53: 1699 | K53: FLAT10 | L53: 10 | M53: Credit Card | N53: Website | O53: Kochi | P53: Kerala | Q53: Bangalore | R53: 2024-10-21 | S53: Delivered | T53: No | W53: Not Applicable
A54: UT-100053 | B54: 2024-10-13 | C54: CUST_10052 | D54: New | E54: OUT-BOM-M | F54: Outerwear | G54: Bomber Jacket | H54: 3799 | I54: 1 | J54: 3799 | L54: 0 | M54: UPI | N54: Mobile App | O54: Vizag | P54: Andhra Pradesh | Q54: Bangalore | R54: 2024-10-23 | S54: Delivered | T54: Yes | U54: Size Issue | V54: 2024-11-18 | W54: Processed
A55: UT-100054 | B55: 2024-10-13 | C55: CUST_10053 | D55: Returning | E55: ACC-NCK-OS | F55: Accessories | G55: Pendant Necklace | H55: 1299 | I55: 1 | J55: 1299 | L55: 0 | M55: COD | N55: Instagram Shop | O55: Thiruvananthapuram | P55: Kerala | Q55: Bangalore | R55: 2024-10-22 | S55: Delivered | T55: No | W55: Not Applicable
A56: UT-100055 | B56: 2024-10-13 | C56: CUST_10054 | D56: New | E56: BOT-WID-M | F56: Bottoms | G56: Wide Leg Pants | H56: 2099 | I56: 1 | J56: 2099 | K56: DIWALI20 | L56: 20 | M56: Credit Card | N56: Website | O56: Mysore | P56: Karnataka | Q56: Bangalore | R56: 2024-10-24 | S56: Delivered | T56: No | W56: Not Applicable
A57: UT-100056 | B57: 2024-10-14 | C57: CUST_10055 | D57: New | E57: DRS-TIR-S | F57: Dresses | G57: Tiered Dress | H57: 2799 | I57: 1 | J57: 2799 | L57: 0 | M57: Debit Card | N57: Mobile App | O57: Vadodara | P57: Gujarat | Q57: Mumbai | R57: 2024-10-23 | S57: Delivered | T57: Yes | U57: Changed Mind | V57: 2024-11-16 | W57: Processed
A58: UT-100057 | B58: 2024-10-14 | C58: CUST_10056 | D58: New | E58: TOP-PEP-M | F58: Tops | G58: Peplum Top | H58: 1499 | I58: 1 | J58: 1499 | L58: 0 | M58: Wallet | N58: Website | O58: Rajkot | P58: Gujarat | Q58: Mumbai | R58: 2024-10-22 | S58: Delivered | T58: No | W58: Not Applicable
A59: UT-100058 | B59: 2024-10-14 | C59: CUST_10057 | D59: Returning | E59: OUT-QTD-L | F59: Outerwear | G59: Quilted Jacket | H59: 4499 | I59: 1 | J59: 4499 | K59: FIRST15 | L59: 15 | M59: UPI | N59: Instagram Shop | O59: Kanpur | P59: Uttar Pradesh | Q59: Delhi | R59: 2024-10-25 | S59: Delivered | T59: Yes | U59: Wrong Item | V59: 2024-11-20 | W59: Processed
A60: UT-100059 | B60: 2024-10-14 | C60: CUST_10058 | D60: New | E60: ACC-BRC-OS | F60: Accessories | G60: Charm Bracelet | H60: 899 | I60: 1 | J60: 899 | L60: 0 | M60: Credit Card | N60: Mobile App | O60: Mumbai | P60: Maharashtra | Q60: Mumbai | R60: 2024-10-23 | S60: Delivered | T60: No | W60: Not Applicable
A61: UT-100060 | B61: 2024-10-15 | C61: CUST_10059 | D61: New | E61: BOT-CRP-S | F61: Bottoms | G61: Cropped Pants | H61: 1799 | I61: 1 | J61: 1799 | L61: 0 | M61: COD | N61: Website | O61: Delhi | P61: Delhi | Q61: Delhi | S61: RTO | T61: No | W61: Not Applicable
A62: UT-100061 | B62: 2024-10-15 | C62: CUST_10060 | D62: New | E62: DRS-SLP-M | F62: Dresses | G62: Slip Dress | H62: 2199 | I62: 1 | J62: 2199 | K62: DIWALI20 | L62: 20 | M62: Debit Card | N62: Instagram Shop | O62: Kolkata | P62: West Bengal | Q62: Delhi | R62: 2024-10-26 | S62: Delivered | T62: Yes | U62: Size Issue | V62: 2024-11-22 | W62: Processed
A63: UT-100062 | B63: 2024-10-15 | C63: CUST_10061 | D63: Returning | E63: TOP-HLT-L | F63: Tops | G63: Halter Top | H63: 1399 | I63: 1 | J63: 1399 | L63: 0 | M63: UPI | N63: Mobile App | O63: Chennai | P63: Tamil Nadu | Q63: Bangalore | R63: 2024-10-24 | S63: Delivered | T63: No | W63: Not Applicable
A64: UT-100063 | B64: 2024-10-15 | C64: CUST_10062 | D64: New | E64: OUT-FLC-M | F64: Outerwear | G64: Fleece Jacket | H64: 2999 | I64: 1 | J64: 2999 | L64: 0 | M64: Credit Card | N64: Website | O64: Hyderabad | P64: Telangana | Q64: Bangalore | R64: 2024-10-27 | S64: Delivered | T64: Yes | U64: Quality Defect | V64: 2024-11-24 | W64: Processed
A65: UT-100064 | B65: 2024-10-16 | C65: CUST_10063 | D65: New | E65: ACC-RNG-OS | F65: Accessories | G65: Cocktail Ring | H65: 699 | I65: 2 | J65: 1398 | K65: FLAT10 | L65: 10 | M65: Wallet | N65: Instagram Shop | O65: Pune | P65: Maharashtra | Q65: Mumbai | R65: 2024-10-25 | S65: Delivered | T65: No | W65: Not Applicable
A66: UT-100065 | B66: 2024-10-16 | C66: CUST_10064 | D66: New | E66: BOT-SKN-M | F66: Bottoms | G66: Skinny Jeans | H66: 2199 | I66: 1 | J66: 2199 | L66: 0 | M66: COD | N66: Mobile App | O66: Ahmedabad | P66: Gujarat | Q66: Mumbai | R66: 2024-10-28 | S66: Delivered | T66: Yes | U66: Size Issue | V66: 2024-11-25 | W66: Processed
A67: UT-100066 | B67: 2024-10-16 | C67: CUST_10065 | D67: Returning | E67: DRS-KNT-S | F67: Dresses | G67: Knit Dress | H67: 2499 | I67: 1 | J67: 2499 | L67: 0 | M67: Credit Card | N67: Website | O67: Jaipur | P67: Rajasthan | Q67: Delhi | R67: 2024-10-26 | S67: Delivered | T67: No | W67: Not Applicable
A68: UT-100067 | B68: 2024-10-16 | C68: CUST_10066 | D68: New | E68: TOP-EMB-M | F68: Tops | G68: Embroidered Top | H68: 1899 | I68: 1 | J68: 1899 | K68: DIWALI20 | L68: 20 | M68: UPI | N68: Instagram Shop | O68: Lucknow | P68: Uttar Pradesh | Q68: Delhi | R68: 2024-10-27 | S68: Delivered | T68: Yes | U68: Changed Mind | V68: 2024-11-20 | W68: Processed
A69: UT-100068 | B69: 2024-10-17 | C69: CUST_10067 | D69: New | E69: OUT-SHR-L | F69: Outerwear | G69: Shrug | H69: 1299 | I69: 1 | J69: 1299 | L69: 0 | M69: Debit Card | N69: Mobile App | O69: Bangalore | P69: Karnataka | Q69: Bangalore | R69: 2024-10-28 | S69: Delivered | T69: No | W69: Not Applicable
A70: UT-100069 | B70: 2024-10-17 | C70: CUST_10068 | D70: New | E70: ACC-CLT-OS | F70: Accessories | G70: Clutch Bag | H70: 1599 | I70: 1 | J70: 1599 | L70: 0 | M70: Credit Card | N70: Website | O70: Mumbai | P70: Maharashtra | Q70: Mumbai | R70: 2024-10-27 | S70: Delivered | T70: Yes | U70: Damaged in Transit | V70: 2024-11-22 | W70: Processed
A71: UT-100070 | B71: 2024-10-17 | C71: CUST_10069 | D71: Returning | E71: BOT-FLR-S | F71: Bottoms | G71: Flared Jeans | H71: 2099 | I71: 1 | J71: 2099 | K71: FIRST15 | L71: 15 | M71: UPI | N71: Instagram Shop | O71: Delhi | P71: Delhi | Q71: Delhi | R71: 2024-10-29 | S71: Delivered | T71: No | W71: Not Applicable
A72: UT-100071 | B72: 2024-10-17 | C72: CUST_10070 | D72: New | E72: DRS-PIN-M | F72: Dresses | G72: Pinafore Dress | H72: 2299 | I72: 1 | J72: 2299 | L72: 0 | M72: COD | N72: Mobile App | O72: Chandigarh | P72: Punjab | Q72: Delhi | S72: RTO | T72: No | W72: Not Applicable
A73: UT-100072 | B73: 2024-10-18 | C73: CUST_10071 | D73: New | E73: TOP-CRW-L | F73: Tops | G73: Crew Neck Tee | H73: 1199 | I73: 2 | J73: 2398 | L73: 0 | M73: Wallet | N73: Website | O73: Noida | P73: Uttar Pradesh | Q73: Delhi | R73: 2024-10-28 | S73: Delivered | T73: No | W73: Not Applicable
A74: UT-100073 | B74: 2024-10-18 | C74: CUST_10072 | D74: New | E74: OUT-CDG-M | F74: Outerwear | G74: Cardigan | H74: 2599 | I74: 1 | J74: 2599 | K74: DIWALI20 | L74: 20 | M74: Credit Card | N74: Instagram Shop | O74: Gurgaon | P74: Haryana | Q74: Delhi | R74: 2024-10-30 | S74: Delivered | T74: Yes | U74: Size Issue | V74: 2024-11-26 | W74: Processed
A75: UT-100074 | B75: 2024-10-18 | C75: CUST_10073 | D75: Returning | E75: ACC-SCR-OS | F75: Accessories | G75: Hair Scrunchie | H75: 299 | I75: 5 | J75: 1495 | L75: 0 | M75: UPI | N75: Mobile App | O75: Indore | P75: Madhya Pradesh | Q75: Mumbai | R75: 2024-10-27 | S75: Delivered | T75: No | W75: Not Applicable
A76: UT-100075 | B76: 2024-10-18 | C76: CUST_10074 | D76: New | E76: BOT-PPR-M | F76: Bottoms | G76: Paper Bag Pants | H76: 1899 | I76: 1 | J76: 1899 | L76: 0 | M76: Debit Card | N76: Website | O76: Surat | P76: Gujarat | Q76: Mumbai | R76: 2024-10-30 | S76: Delivered | T76: Yes | U76: Wrong Item | V76: 2024-11-28 | W76: Processed
A77: UT-100076 | B77: 2024-10-19 | C77: CUST_10075 | D77: New | E77: DRS-SMK-S | F77: Dresses | G77: Smocked Dress | H77: 2199 | I77: 1 | J77: 2199 | L77: 0 | M77: Credit Card | N77: Instagram Shop | O77: Patna | P77: Bihar | Q77: Delhi | R77: 2024-10-31 | S77: Delivered | T77: No | W77: Not Applicable
A78: UT-100077 | B78: 2024-10-19 | C78: CUST_10076 | D78: New | E78: TOP-BTN-M | F78: Tops | G78: Button-Down Shirt | H78: 1799 | I78: 1 | J78: 1799 | K78: FLAT10 | L78: 10 | M78: COD | N78: Mobile App | O78: Bhopal | P78: Madhya Pradesh | Q78: Mumbai | R78: 2024-10-29 | S78: Delivered | T78: Yes | U78: Quality Defect | V78: 2024-11-25 | W78: Processed
A79: UT-100078 | B79: 2024-10-19 | C79: CUST_10077 | D79: Returning | E79: OUT-VLV-L | F79: Outerwear | G79: Velvet Blazer | H79: 4999 | I79: 1 | J79: 4999 | L79: 0 | M79: UPI | N79: Website | O79: Nagpur | P79: Maharashtra | Q79: Mumbai | R79: 2024-11-01 | S79: Delivered | T79: No | W79: Not Applicable
A80: UT-100079 | B80: 2024-10-19 | C80: CUST_10078 | D80: New | E80: ACC-TOT-OS | F80: Accessories | G80: Canvas Tote | H80: 999 | I80: 1 | J80: 999 | L80: 0 | M80: Wallet | N80: Instagram Shop | O80: Coimbatore | P80: Tamil Nadu | Q80: Bangalore | R80: 2024-10-30 | S80: Delivered | T80: Yes | U80: Size Issue | V80: 2024-11-28 | W80: Processed
A81: UT-100080 | B81: 2024-10-20 | C81: CUST_10079 | D81: New | E81: BOT-CRG-S | F81: Bottoms | G81: Cargo Shorts | H81: 1499 | I81: 1 | J81: 1499 | K81: DIWALI20 | L81: 20 | M81: Credit Card | N81: Mobile App | O81: Kochi | P81: Kerala | Q81: Bangalore | R81: 2024-10-31 | S81: Delivered | T81: No | W81: Not Applicable
A82: UT-100081 | B82: 2024-10-20 | C82: CUST_10080 | D82: New | E82: DRS-BTR-M | F82: Dresses | G82: Butterfly Dress | H82: 2899 | I82: 1 | J82: 2899 | L82: 0 | M82: Debit Card | N82: Website | O82: Vizag | P82: Andhra Pradesh | Q82: Bangalore | R82: 2024-11-02 | S82: Delivered | T82: Yes | U82: Changed Mind | V82: 2024-11-30 | W82: Processed
A83: UT-100082 | B83: 2024-10-20 | C83: CUST_10081 | D83: Returning | E83: TOP-VNK-L | F83: Tops | G83: V-Neck Tee | H83: 1099 | I83: 2 | J83: 2198 | L83: 0 | M83: UPI | N83: Instagram Shop | O83: Thiruvananthapuram | P83: Kerala | Q83: Bangalore | R83: 2024-10-30 | S83: Delivered | T83: No | W83: Not Applicable
A84: UT-100083 | B84: 2024-10-20 | C84: CUST_10082 | D84: New | E84: OUT-TRN-M | F84: Outerwear | G84: Trench Coat | H84: 5499 | I84: 1 | J84: 5499 | K84: FIRST15 | L84: 15 | M84: Credit Card | N84: Mobile App | O84: Mysore | P84: Karnataka | Q84: Bangalore | R84: 2024-11-03 | S84: Delivered | T84: Yes | U84: Size Issue | V84: 2024-12-01 | W84: Processed
A85: UT-100084 | B85: 2024-10-21 | C85: CUST_10083 | D85: New | E85: ACC-BDY-OS | F85: Accessories | G85: Body Chain | H85: 799 | I85: 1 | J85: 799 | L85: 0 | M85: COD | N85: Website | O85: Vadodara | P85: Gujarat | Q85: Mumbai | S85: RTO | T85: No | W85: Not Applicable
A86: UT-100085 | B86: 2024-10-21 | C86: CUST_10084 | D86: New | E86: BOT-JGR-L | F86: Bottoms | G86: Jogger Pants | H86: 1599 | I86: 1 | J86: 1599 | L86: 0 | M86: Wallet | N86: Instagram Shop | O86: Rajkot | P86: Gujarat | Q86: Mumbai | R86: 2024-11-02 | S86: Delivered | T86: No | W86: Not Applicable
A87: UT-100086 | B87: 2024-10-21 | C87: CUST_10085 | D87: Returning | E87: DRS-RFL-S | F87: Dresses | G87: Ruffle Dress | H87: 2699 | I87: 1 | J87: 2699 | K87: DIWALI20 | L87: 20 | M87: Credit Card | N87: Mobile App | O87: Kanpur | P87: Uttar Pradesh | Q87: Delhi | R87: 2024-11-01 | S87: Delivered | T87: Yes | U87: Quality Defect | V87: 2024-11-30 | W87: Processed
A88: UT-100087 | B88: 2024-10-21 | C88: CUST_10086 | D88: New | E88: TOP-SQR-M | F88: Tops | G88: Square Neck Top | H88: 1499 | I88: 1 | J88: 1499 | L88: 0 | M88: UPI | N88: Website | O88: Mumbai | P88: Maharashtra | Q88: Mumbai | R88: 2024-11-02 | S88: Delivered | T88: No | W88: Not Applicable
A89: UT-100088 | B89: 2024-10-22 | C89: CUST_10087 | D89: New | E89: OUT-WND-L | F89: Outerwear | G89: Windbreaker | H89: 3299 | I89: 1 | J89: 3299 | L89: 0 | M89: Debit Card | N89: Instagram Shop | O89: Delhi | P89: Delhi | Q89: Delhi | R89: 2024-11-04 | S89: Delivered | T89: Yes | U89: Wrong Item | V89: 2024-12-03 | W89: Processed
A90: UT-100089 | B90: 2024-10-22 | C90: CUST_10088 | D90: New | E90: ACC-ANK-OS | F90: Accessories | G90: Anklet | H90: 499 | I90: 2 | J90: 998 | K90: FLAT10 | L90: 10 | M90: Credit Card | N90: Mobile App | O90: Kolkata | P90: West Bengal | Q90: Delhi | R90: 2024-11-01 | S90: Delivered | T90: No | W90: Not Applicable
A91: UT-100090 | B91: 2024-10-22 | C91: CUST_10089 | D91: Returning | E91: BOT-TRS-M | F91: Bottoms | G91: Tailored Trousers | H91: 2399 | I91: 1 | J91: 2399 | L91: 0 | M91: UPI | N91: Website | O91: Chennai | P91: Tamil Nadu | Q91: Bangalore | R91: 2024-11-03 | S91: Delivered | T91: No | W91: Not Applicable
A92: UT-100091 | B92: 2024-10-22 | C92: CUST_10090 | D92: New | E92: DRS-LST-M | F92: Dresses | G92: Lace Trim Dress | H92: 2599 | I92: 1 | J92: 2599 | L92: 0 | M92: COD | N92: Instagram Shop | O92: Hyderabad | P92: Telangana | Q92: Bangalore | S92: RTO | T92: No | W92: Not Applicable
A93: UT-100092 | B93: 2024-10-23 | C93: CUST_10091 | D93: New | E93: TOP-TIE-S | F93: Tops | G93: Tie-Front Top | H93: 1399 | I93: 1 | J93: 1399 | K93: DIWALI20 | L93: 20 | M93: Wallet | N93: Mobile App | O93: Pune | P93: Maharashtra | Q93: Mumbai | R93: 2024-11-03 | S93: Delivered | T93: Yes | U93: Size Issue | V93: 2024-12-02 | W93: Processed
A94: UT-100093 | B94: 2024-10-23 | C94: CUST_10092 | D94: New | E94: OUT-PUF-M | F94: Outerwear | G94: Puffer Jacket | H94: 4299 | I94: 1 | J94: 4299 | L94: 0 | M94: Credit Card | N94: Website | O94: Ahmedabad | P94: Gujarat | Q94: Mumbai | R94: 2024-11-05 | S94: Delivered | T94: No | W94: Not Applicable
A95: UT-100094 | B95: 2024-10-23 | C95: CUST_10093 | D95: Returning | E95: ACC-HDR-OS | F95: Accessories | G95: Hairband | H95: 399 | I95: 3 | J95: 1197 | L95: 0 | M95: UPI | N95: Instagram Shop | O95: Jaipur | P95: Rajasthan | Q95: Delhi | R95: 2024-11-02 | S95: Delivered | T95: No | W95: Not Applicable
A96: UT-100095 | B96: 2024-10-23 | C96: CUST_10094 | D96: New | E96: BOT-PLT-L | F96: Bottoms | G96: Pleated Trousers | H96: 2199 | I96: 1 | J96: 2199 | K96: FIRST15 | L96: 15 | M96: Debit Card | N96: Mobile App | O96: Lucknow | P96: Uttar Pradesh | Q96: Delhi | R96: 2024-11-05 | S96: Delivered | T96: Yes | U96: Damaged in Transit | V96: 2024-12-05 | W96: Processed
A97: UT-100096 | B97: 2024-10-24 | C97: CUST_10095 | D97: New | E97: DRS-SHR-S | F97: Dresses | G97: Shirtdress | H97: 2399 | I97: 1 | J97: 2399 | L97: 0 | M97: Credit Card | N97: Website | O97: Bangalore | P97: Karnataka | Q97: Bangalore | R97: 2024-11-04 | S97: Delivered | T97: No | W97: Not Applicable
A98: UT-100097 | B98: 2024-10-24 | C98: CUST_10096 | D98: New | E98: TOP-GRF-M | F98: Tops | G98: Graphic Tee | H98: 1299 | I98: 1 | J98: 1299 | L98: 0 | M98: COD | N98: Instagram Shop | O98: Mumbai | P98: Maharashtra | Q98: Mumbai | R98: 2024-11-06 | S98: Delivered | T98: Yes | U98: Changed Mind | V98: 2024-12-05 | W98: Processed
A99: UT-100098 | B99: 2024-10-24 | C99: CUST_10097 | D99: Returning | E99: OUT-SHW-L | F99: Outerwear | G99: Shawl Wrap | H99: 2799 | I99: 1 | J99: 2799 | K99: DIWALI20 | L99: 20 | M99: UPI | N99: Mobile App | O99: Delhi | P99: Delhi | Q99: Delhi | R99: 2024-11-05 | S99: Delivered | T99: No | W99: Not Applicable
A100: UT-100099 | B100: 2024-10-24 | C100: CUST_10098 | D100: New | E100: ACC-BLT-S | F100: Accessories | G100: Braided Belt | H100: 699 | I100: 1 | J100: 699 | L100: 0 | M100: Wallet | N100: Website | O100: Chandigarh | P100: Punjab | Q100: Delhi | R100: 2024-11-04 | S100: Delivered | T100: No | W100: Not Applicable
...

Sheet Working_Data
A1: Order ID | B1: Order Date | C1: Customer ID | D1: Type | E1: SKU | F1: Category | G1: Product Name | H1: Unit Price | I1: Qty | J1: Total | K1: Discount Code | L1: Disc % | M1: Payment | N1: Source | O1: City | P1: State | Q1: Warehouse | R1: Del Date | S1: Status | T1: Return? | U1: Reason | V1: Ret Rec | W1: Refund | Y1: Week_Start | Z1: Delivery Days | AA1: Discount Trap
A2: UT-100001 | B2: 2024-10-01 | C2: CUST_10001 | D2: New | E2: TOP-CAS-M | F2: Tops | G2: Classic Cotton Tee | H2: 1299 | I2: 2 | J2: 2598 | L2: 0 | M2: UPI | N2: Website | O2: Mumbai | P2: Maharashtra | Q2: Mumbai | R2: 2024-10-05 | S2: Delivered | T2: No | W2: Not Applicable | Y2: =B2 - WEEKDAY(B2,2) + 1 -> 2024-09-30 | Z2: =IF(R2<>"", R2-B2, "") -> 4 | AA2: =IF(L2=0, "No Discount", IF(L2<=20, "Low (1-20%)", "High (20%+)")) -> No Discount
A3: UT-100002 | B3: 2024-10-01 | C3: CUST_10002 | D3: Returning | E3: DRS-FRM-S | F3: Dresses | G3: Floral Midi Dress | H3: 2499 | I3: 1 | J3: 2499 | K3: DIWALI20 | L3: 20 | M3: Credit Card | N3: Mobile App | O3: Delhi | P3: Delhi | Q3: Delhi | R3: 2024-10-04 | S3: Delivered | T3: Yes | U3: Size Issue | V3: 2024-10-15 | W3: Processed | Y3: =B3 - WEEKDAY(B3,2) + 1 -> 2024-09-30 | Z3: =IF(R3<>"", R3-B3, "") -> 3 | AA3: =IF(L3=0, "No Discount", IF(L3<=20, "Low (1-20%)", "High (20%+)")) -> Low (1-20%)
A4: UT-100003 | B4: 2024-10-01 | C4: CUST_10003 | D4: new | E4: BOT-JNS-L | F4: Bottoms | G4: Slim Fit Jeans | H4: 1899 | I4: 1 | J4: 1899 | L4: 0 | M4: COD | N4: Website | O4: Bangalore | P4: Karnataka | Q4: Bangalore | R4: 2024-10-06 | S4: Delivered | T4: No | W4: Not Applicable | Y4: =B4 - WEEKDAY(B4,2) + 1 -> 2024-09-30 | Z4: =IF(R4<>"", R4-B4, "") -> 5 | AA4: =IF(L4=0, "No Discount", IF(L4<=20, "Low (1-20%)", "High (20%+)")) -> No Discount
A5: UT-100004 | B5: 2024-10-01 | C5: CUST_10004 | D5: New | E5: OUT-JKT-XL | F5: Outerwear | G5: Denim Jacket | H5: 3499 | I5: 1 | J5: 3499 | K5: FIRST15 | L5: 15 | M5: Debit Card | N5: Instagram Shop | O5: Chennai | P5: Tamil Nadu | Q5: Mumbai | R5: 2024-10-08 | S5: Delivered | T5: Yes | U5: Quality Defect | V5: 2024-10-20 | W5: Processed | Y5: =B5 - WEEKDAY(B5,2) + 1 -> 2024-09-30 | Z5: =IF(R5<>"", R5-B5, "") -> 7 | AA5: =IF(L5=0, "No Discount", IF(L5<=20, "Low (1-20%)", "High (20%+)")) -> Low (1-20%)
A6: UT-100005 | B6: 2024-10-01 | C6: CUST_10001 | D6: New | E6: ACC-SCF-OS | F6: Accessories | G6: Silk Scarf | H6: 799 | I6: 3 | J6: 2397 | L6: 0 | M6: UPI | N6: Website | O6: Mumbai | P6: Maharashtra | Q6: Mumbai | R6: 2024-10-06 | S6: Delivered | T6: No | W6: Not Applicable | Y6: =B6 - WEEKDAY(B6,2) + 1 -> 2024-09-30 | Z6: =IF(R6<>"", R6-B6, "") -> 5 | AA6: =IF(L6=0, "No Discount", IF(L6<=20, "Low (1-20%)", "High (20%+)")) -> No Discount
A7: UT-100006 | B7: 2024-10-02 | C7: CUST_10005 | D7: Returning | E7: TOP-FRM-S | F7: Tops | G7: Printed Blouse | H7: 1599 | I7: 2 | J7: 3198 | L7: 0 | M7: Credit Card | N7: Mobile App | O7: Hyderabad | P7: Telangana | Q7: Bangalore | R7: 2024-10-07 | S7: Delivered | T7: Yes | U7: Changed Mind | V7: 2024-10-18 | W7: Processed | Y7: =B7 - WEEKDAY(B7,2) + 1 -> 2024-09-30 | Z7: =IF(R7<>"", R7-B7, "") -> 5 | AA7: =IF(L7=0, "No Discount", IF(L7<=20, "Low (1-20%)", "High (20%+)")) -> No Discount
A8: UT-100007 | B8: 2024-10-02 | C8: CUST_10006 | D8: New | E8: DRS-CAS-M | F8: Dresses | G8: A-Line Dress | H8: 2199 | I8: 1 | J8: 2199 | K8: DIWALI20 | L8: 20 | M8: COD | N8: Website | O8: Pune | P8: Maharashtra | Q8: Mumbai | S8: Cancelled | T8: No | W8: Not Applicable | Y8: =B8 - WEEKDAY(B8,2) + 1 -> 2024-09-30 | Z8: =IF(R8<>"", R8-B8, "") | AA8: =IF(L8=0, "No Discount", IF(L8<=20, "Low (1-20%)", "High (20%+)")) -> Low (1-20%)
A9: UT-100008 | B9: 2024-10-02 | C9: CUST_10007 | D9: New | E9: BOT-TRS-L | F9: Bottoms | G9: Formal Trousers | H9: 2299 | I9: 1 | J9: 2299 | L9: 0 | M9: UPI | N9: Mobile App | O9: Kolkata | P9: West Bengal | Q9: Delhi | R9: 2024-10-10 | S9: Delivered | T9: No | W9: Not Applicable | Y9: =B9 - WEEKDAY(B9,2) + 1 -> 2024-09-30 | Z9: =IF(R9<>"", R9-B9, "") -> 8 | AA9: =IF(L9=0, "No Discount", IF(L9<=20, "Low (1-20%)", "High (20%+)")) -> No Discount
A10: UT-100009 | B10: 2024-10-02 | C10: CUST_10008 | D10: Returning | E10: TOP-CAS-XL | F10: Tops | G10: Oversized Tee | H10: 1399 | I10: 5 | J10: 6995 | L10: 0 | M10: Credit Card | N10: Website | O10: Ahmedabad | P10: Gujarat | Q10: Mumbai | R10: 2024-10-09 | S10: Delivered | T10: Yes | U10: Size Issue | V10: 2024-10-22 | W10: Processed | Y10: =B10 - WEEKDAY(B10,2) + 1 -> 2024-09-30 | Z10: =IF(R10<>"", R10-B10, "") -> 7 | AA10: =IF(L10=0, "No Discount", IF(L10<=20, "Low (1-20%)", "High (20%+)")) -> No Discount
A11: UT-100010 | B11: 2024-10-02 | C11: CUST_10009 | D11: New | E11: OUT-BLZ-M | F11: Outerwear | G11: Casual Blazer | H11: 4999 | I11: -1 | J11: 4999 | L11: 0 | M11: Debit Card | N11: Instagram Shop | O11: Jaipur | P11: Rajasthan | Q11: Delhi | R11: 2024-10-11 | S11: Delivered | T11: Yes | U11: Wrong Item | V11: 2024-10-25 | W11: Pending | Y11: =B11 - WEEKDAY(B11,2) + 1 -> 2024-09-30 | Z11: =IF(R11<>"", R11-B11, "") -> 9 | AA11: =IF(L11=0, "No Discount", IF(L11<=20, "Low (1-20%)", "High (20%+)")) -> No Discount
A12: UT-100011 | B12: 2024-10-03 | C12: CUST_10010 | D12: New | E12: ACC-BAG-OS | F12: Accessories | G12: Tote Bag | H12: 1299 | I12: 2 | J12: 2598 | K12: FLAT10 | L12: 10 | M12: Wallet | N12: Website | O12: Lucknow | P12: Uttar Pradesh | Q12: Delhi | R12: 2024-10-10 | S12: Delivered | T12: No | W12: Not Applicable | Y12: =B12 - WEEKDAY(B12,2) + 1 -> 2024-09-30 | Z12: =IF(R12<>"", R12-B12, "") -> 7 | AA12: =IF(L12=0, "No Discount", IF(L12<=20, "Low (1-20%)", "High (20%+)")) -> Low (1-20%)
A13: UT-100012 | B13: 2024-10-03 | C13: CUST_10011 | D13: New | E13: DRS-PRT-S | F13: Dresses | G13: Party Dress | H13: 3299 | I13: 1 | J13: 3299 | L13: 0 | M13: COD | N13: Mobile App | O13: Chandigarh | P13: Punjab | Q13: Delhi | S13: RTO | T13: No | W13: Not Applicable | Y13: =B13 - WEEKDAY(B13,2) + 1 -> 2024-09-30 | Z13: =IF(R13<>"", R13-B13, "") | AA13: =IF(L13=0, "No Discount", IF(L13<=20, "Low (1-20%)", "High (20%+)")) -> No Discount
A14: UT-100013 | B14: 2024-10-03 | C14: CUST_10012 | D14: Returning | E14: TOP-SLK-M | F14: Tops | G14: Silk Blouse | H14: 2499 | I14: 1 | J14: 2499 | L14: 0 | M14: Credit Card | N14: Website | O14: Mumbai | P14: Maharashtra | Q14: Mumbai | R14: 2024-10-09 | S14: Delivered | T14: No | W14: Not Applicable | Y14: =B14 - WEEKDAY(B14,2) + 1 -> 2024-09-30 | Z14: =IF(R14<>"", R14-B14, "") -> 6 | AA14: =IF(L14=0, "No Discount", IF(L14<=20, "Low (1-20%)", "High (20%+)")) -> No Discount
A15: UT-100014 | B15: 2024-10-03 | C15: CUST_10013 | D15: New | E15: BOT-SKT-S | F15: Bottoms | G15: Pleated Skirt | H15: 1799 | I15: 2 | J15: 3598 | K15: DIWALI20 | L15: 20 | M15: UPI | N15: Instagram Shop | O15: Delhi | P15: Delhi | Q15: Delhi | R15: 2024-10-11 | S15: Delivered | T15: Yes | U15: Size Issue | V15: 2024-10-28 | W15: Processed | Y15: =B15 - WEEKDAY(B15,2) + 1 -> 2024-09-30 | Z15: =IF(R15<>"", R15-B15, "") -> 8 | AA15: =IF(L15=0, "No Discount", IF(L15<=20, "Low (1-20%)", "High (20%+)")) -> Low (1-20%)
A16: UT-100015 | B16: 2024-10-03 | C16: CUST_10014 | D16: New | E16: OUT-CRD-L | F16: Outerwear | G16: Knit Cardigan | H16: 2799 | I16: 1 | J16: 2799 | L16: 0 | M16: Debit Card | N16: Mobile App | O16: Bangalore | P16: Karnataka | Q16: Bangalore | R16: 2024-10-12 | S16: Delivered | T16: No | W16: Not Applicable | Y16: =B16 - WEEKDAY(B16,2) + 1 -> 2024-09-30 | Z16: =IF(R16<>"", R16-B16, "") -> 9 | AA16: =IF(L16=0, "No Discount", IF(L16<=20, "Low (1-20%)", "High (20%+)")) -> No Discount
A17: UT-100016 | B17: 2024-10-04 | C17: CUST_10015 | D17: Returning | E17: ACC-JWL-OS | F17: Accessories | G17: Statement Earrings | H17: 599 | I17: 4 | J17: 2396 | L17: 0 | M17: COD | N17: Website | O17: Noida | P17: Uttar Pradesh | Q17: Delhi | R17: 2024-10-14 | S17: Delivered | T17: Yes | U17: Damaged in Transit | V17: 2024-10-26 | W17: Processed | Y17: =B17 - WEEKDAY(B17,2) + 1 -> 2024-09-30 | Z17: =IF(R17<>"", R17-B17, "") -> 10 | AA17: =IF(L17=0, "No Discount", IF(L17<=20, "Low (1-20%)", "High (20%+)")) -> No Discount
A18: UT-100017 | B18: 2024-10-04 | C18: CUST_10016 | D18: New | E18: TOP-CRP-XS | F18: Tops | G18: Crop Top | H18: 999 | I18: 1 | J18: 999 | K18: FIRST15 | L18: 15 | M18: UPI | N18: Mobile App | O18: Gurgaon | P18: Haryana | Q18: Delhi | R18: 2024-10-12 | S18: Delivered | T18: No | W18: Not Applicable | Y18: =B18 - WEEKDAY(B18,2) + 1 -> 2024-09-30 | Z18: =IF(R18<>"", R18-B18, "") -> 8 | AA18: =IF(L18=0, "No Discount", IF(L18<=20, "Low (1-20%)", "High (20%+)")) -> Low (1-20%)
A19: UT-100018 | B19: 2024-10-04 | C19: CUST_10017 | D19: New | E19: DRS-MAX-M | F19: Dresses | G19: Maxi Dress | H19: 2899 | I19: 1 | J19: 2899 | L19: 0 | M19: Credit Card | N19: Website | O19: Indore | P19: Madhya Pradesh | Q19: Mumbai | R19: 2024-10-14 | S19: Delivered | T19: No | W19: Not Applicable | Y19: =B19 - WEEKDAY(B19,2) + 1 -> 2024-09-30 | Z19: =IF(R19<>"", R19-B19, "") -> 10 | AA19: =IF(L19=0, "No Discount", IF(L19<=20, "Low (1-20%)", "High (20%+)")) -> No Discount
A20: UT-100019 | B20: 2024-10-04 | C20: CUST_10018 | D20: Returning | E20: BOT-JGR-M | F20: Bottoms | G20: Joggers | H20: 1499 | I20: 2 | J20: 2998 | L20: 0 | M20: Wallet | N20: Instagram Shop | O20: Surat | P20: Gujarat | Q20: Mumbai | R20: 2024-10-13 | S20: Delivered | T20: Yes | U20: Size Issue | V20: 2024-10-30 | W20: Processed | Y20: =B20 - WEEKDAY(B20,2) + 1 -> 2024-09-30 | Z20: =IF(R20<>"", R20-B20, "") -> 9 | AA20: =IF(L20=0, "No Discount", IF(L20<=20, "Low (1-20%)", "High (20%+)")) -> No Discount
A21: UT-100020 | B21: 2024-10-05 | C21: CUST_10019 | D21: New | E21: OUT-VST-S | F21: Outerwear | G21: Puffer Vest | H21: 3999 | I21: 1 | J21: 3999 | K21: DIWALI20 | L21: 20 | M21: COD | N21: Website | O21: Patna | P21: Bihar | Q21: Delhi | S21: RTO | T21: No | W21: Not Applicable | Y21: =B21 - WEEKDAY(B21,2) + 1 -> 2024-09-30 | Z21: =IF(R21<>"", R21-B21, "") | AA21: =IF(L21=0, "No Discount", IF(L21<=20, "Low (1-20%)", "High (20%+)")) -> Low (1-20%)
A22: UT-100021 | B22: 2024-10-05 | C22: CUST_10020 | D22: New | E22: TOP-TUN-L | F22: Tops | G22: Tunic Top | H22: 1699 | I22: 1 | J22: 1699 | L22: 0 | M22: UPI | N22: Mobile App | O22: Bhopal | P22: Madhya Pradesh | Q22: Mumbai | R22: 2024-10-15 | S22: Delivered | T22: No | W22: Not Applicable | Y22: =B22 - WEEKDAY(B22,2) + 1 -> 2024-09-30 | Z22: =IF(R22<>"", R22-B22, "") -> 10 | AA22: =IF(L22=0, "No Discount", IF(L22<=20, "Low (1-20%)", "High (20%+)")) -> No Discount
A23: UT-100022 | B23: 2024-10-05 | C23: CUST_10021 | D23: Returning | E23: DRS-SHT-XS | F23: Dresses | G23: Shirt Dress | H23: 2399 | I23: 1 | J23: 2399 | L23: 0 | M23: Credit Card | N23: Website | O23: Nagpur | P23: Maharashtra | Q23: Mumbai | R23: 2024-10-16 | S23: Delivered | T23: Yes | U23: Quality Defect | V23: 2024-11-02 | W23: Processed | Y23: =B23 - WEEKDAY(B23,2) + 1 -> 2024-09-30 | Z23: =IF(R23<>"", R23-B23, "") -> 11 | AA23: =IF(L23=0, "No Discount", IF(L23<=20, "Low (1-20%)", "High (20%+)")) -> No Discount
A24: UT-100023 | B24: 2024-10-05 | C24: CUST_10022 | D24: New | E24: ACC-BLT-M | F24: Accessories | G24: Leather Belt | H24: 899 | I24: 1 | J24: 899 | K24: FLAT10 | L24: 10 | M24: Debit Card | N24: Mobile App | O24: Coimbatore | P24: Tamil Nadu | Q24: Bangalore | R24: 2024-10-17 | S24: Delivered | T24: No | W24: Not Applicable | Y24: =B24 - WEEKDAY(B24,2) + 1 -> 2024-09-30 | Z24: =IF(R24<>"", R24-B24, "") -> 12 | AA24: =IF(L24=0, "No Discount", IF(L24<=20, "Low (1-20%)", "High (20%+)")) -> Low (1-20%)
A25: UT-100024 | B25: 2024-10-06 | C25: CUST_10023 | D25: New | E25: BOT-SHT-M | F25: Bottoms | G25: Cotton Shorts | H25: 1199 | I25: 3 | J25: 3597 | L25: 0 | M25: COD | N25: Instagram Shop | O25: Kochi | P25: Kerala | Q25: Bangalore | R25: 2024-10-18 | S25: Delivered | T25: Yes | U25: Changed Mind | V25: 2024-11-05 | W25: Processed | Y25: =B25 - WEEKDAY(B25,2) + 1 -> 2024-09-30 | Z25: =IF(R25<>"", R25-B25, "") -> 12 | AA25: =IF(L25=0, "No Discount", IF(L25<=20, "Low (1-20%)", "High (20%+)")) -> No Discount
A26: UT-100025 | B26: 2024-10-06 | C26: CUST_10024 | D26: New | E26: TOP-PLO-L | F26: Tops | G26: Polo Shirt | H26: 1799 | I26: 2 | J26: 3598 | L26: 0 | M26: UPI | N26: Website | O26: Vizag | P26: Andhra Pradesh | Q26: Bangalore | R26: 2024-10-17 | S26: Delivered | T26: No | W26: Not Applicable | Y26: =B26 - WEEKDAY(B26,2) + 1 -> 2024-09-30 | Z26: =IF(R26<>"", R26-B26, "") -> 11 | AA26: =IF(L26=0, "No Discount", IF(L26<=20, "Low (1-20%)", "High (20%+)")) -> No Discount
A27: UT-100026 | B27: 2024-10-06 | C27: CUST_10025 | D27: New | E27: DRS-WRK-M | F27: Dresses | G27: Work Dress | H27: 2699 | I27: 1 | J27: 2699 | L27: 0 | M27: Credit Card | N27: Mobile App | O27: Thiruvananthapuram | P27: Kerala | Q27: Bangalore | R27: 2024-10-18 | S27: Delivered | T27: No | W27: Not Applicable | Y27: =B27 - WEEKDAY(B27,2) + 1 -> 2024-09-30 | Z27: =IF(R27<>"", R27-B27, "") -> 12 | AA27: =IF(L27=0, "No Discount", IF(L27<=20, "Low (1-20%)", "High (20%+)")) -> No Discount
A28: UT-100027 | B28: 2024-10-06 | C28: CUST_10026 | D28: Returning | E28: OUT-TRN-L | F28: Outerwear | G28: Trench Coat | H28: 4599 | I28: 1 | J28: 4599 | K28: FLAT10 | L28: 10 | M28: Debit Card | N28: Website | O28: Mysore | P28: Karnataka | Q28: Bangalore | R28: 2024-10-19 | S28: Delivered | T28: Yes | U28: Size Issue | V28: 2024-11-08 | W28: Processed | Y28: =B28 - WEEKDAY(B28,2) + 1 -> 2024-09-30 | Z28: =IF(R28<>"", R28-B28, "") -> 13 | AA28: =IF(L28=0, "No Discount", IF(L28<=20, "Low (1-20%)", "High (20%+)")) -> Low (1-20%)
A29: UT-100028 | B29: 2024-10-07 | C29: CUST_10027 | D29: New | E29: ACC-HAT-OS | F29: Accessories | G29: Fedora Hat | H29: 1099 | I29: 1 | J29: 1099 | L29: 0 | M29: UPI | N29: Instagram Shop | O29: Vadodara | P29: Gujarat | Q29: Mumbai | R29: 2024-10-20 | S29: Delivered | T29: No | W29: Not Applicable | Y29: =B29 - WEEKDAY(B29,2) + 1 -> 2024-10-07 | Z29: =IF(R29<>"", R29-B29, "") -> 13 | AA29: =IF(L29=0, "No Discount", IF(L29<=20, "Low (1-20%)", "High (20%+)")) -> No Discount
A30: UT-100029 | B30: 2024-10-07 | C30: CUST_10028 | D30: New | E30: TOP-DNM-M | F30: Tops | G30: Denim Shirt | H30: 1899 | I30: 1 | J30: 1899 | L30: 0 | M30: COD | N30: Mobile App | O30: Rajkot | P30: Gujarat | Q30: Mumbai | S30: RTO | T30: No | W30: Not Applicable | Y30: =B30 - WEEKDAY(B30,2) + 1 -> 2024-10-07 | Z30: =IF(R30<>"", R30-B30, "") | AA30: =IF(L30=0, "No Discount", IF(L30<=20, "Low (1-20%)", "High (20%+)")) -> No Discount
A31: UT-100030 | B31: 2024-10-07 | C31: CUST_10029 | D31: New | E31: BOT-CRG-L | F31: Bottoms | G31: Cargo Pants | H31: 2199 | I31: 1 | J31: 2199 | K31: DIWALI20 | L31: 20 | M31: Credit Card | N31: Website | O31: Kanpur | P31: Uttar Pradesh | Q31: Delhi | R31: 2024-10-20 | S31: Delivered | T31: No | W31: Not Applicable | Y31: =B31 - WEEKDAY(B31,2) + 1 -> 2024-10-07 | Z31: =IF(R31<>"", R31-B31, "") -> 13 | AA31: =IF(L31=0, "No Discount", IF(L31<=20, "Low (1-20%)", "High (20%+)")) -> Low (1-20%)
A32: UT-100031 | B32: 2024-10-07 | C32: CUST_10030 | D32: Returning | E32: DRS-EVE-S | F32: Dresses | G32: Evening Gown | H32: 5499 | I32: 1 | J32: 5499 | L32: 0 | M32: Credit Card | N32: Mobile App | O32: Mumbai | P32: Maharashtra | Q32: Mumbai | R32: 2024-10-21 | S32: Delivered | T32: Yes | U32: Size Issue | V32: 2024-11-10 | W32: Processed | Y32: =B32 - WEEKDAY(B32,2) + 1 -> 2024-10-07 | Z32: =IF(R32<>"", R32-B32, "") -> 14 | AA32: =IF(L32=0, "No Discount", IF(L32<=20, "Low (1-20%)", "High (20%+)")) -> No Discount
A33: UT-100032 | B33: 2024-10-08 | C33: CUST_10031 | D33: New | E33: TOP-BAS-M | F33: Tops | G33: Basic Tank | H33: 899 | I33: 2 | J33: 1798 | L33: 0 | M33: UPI | N33: Website | O33: Delhi | P33: Delhi | Q33: Delhi | R33: 2024-10-14 | S33: Delivered | T33: No | W33: Not Applicable | Y33: =B33 - WEEKDAY(B33,2) + 1 -> 2024-10-07 | Z33: =IF(R33<>"", R33-B33, "") -> 6 | AA33: =IF(L33=0, "No Discount", IF(L33<=20, "Low (1-20%)", "High (20%+)")) -> No Discount
A34: UT-100033 | B34: 2024-10-08 | C34: CUST_10032 | D34: New | E34: OUT-WOL-L | F34: Outerwear | G34: Wool Coat | H34: 6999 | I34: 1 | J34: 6999 | K34: FIRST15 | L34: 15 | M34: Debit Card | N34: Instagram Shop | O34: Kolkata | P34: West Bengal | Q34: Delhi | R34: 2024-10-16 | S34: Delivered | T34: Yes | U34: Quality Defect | V34: 2024-11-05 | W34: Processed | Y34: =B34 - WEEKDAY(B34,2) + 1 -> 2024-10-07 | Z34: =IF(R34<>"", R34-B34, "") -> 8 | AA34: =IF(L34=0, "No Discount", IF(L34<=20, "Low (1-20%)", "High (20%+)")) -> Low (1-20%)
A35: UT-100034 | B35: 2024-10-08 | C35: CUST_10033 | D35: Returning | E35: ACC-WCH-OS | F35: Accessories | G35: Fashion Watch | H35: 2999 | I35: 1 | J35: 2999 | L35: 0 | M35: Credit Card | N35: Mobile App | O35: Chennai | P35: Tamil Nadu | Q35: Bangalore | R35: 2024-10-15 | S35: Delivered | T35: No | W35: Not Applicable | Y35: =B35 - WEEKDAY(B35,2) + 1 -> 2024-10-07 | Z35: =IF(R35<>"", R35-B35, "") -> 7 | AA35: =IF(L35=0, "No Discount", IF(L35<=20, "Low (1-20%)", "High (20%+)")) -> No Discount
A36: UT-100035 | B36: 2024-10-08 | C36: CUST_10034 | D36: New | E36: BOT-DNM-S | F36: Bottoms | G36: Denim Shorts | H36: 1599 | I36: 1 | J36: 1599 | L36: 0 | M36: COD | N36: Website | O36: Hyderabad | P36: Telangana | Q36: Bangalore | R36: 2024-10-17 | S36: Delivered | T36: Yes | U36: Size Issue | V36: 2024-11-08 | W36: Processed | Y36: =B36 - WEEKDAY(B36,2) + 1 -> 2024-10-07 | Z36: =IF(R36<>"", R36-B36, "") -> 9 | AA36: =IF(L36=0, "No Discount", IF(L36<=20, "Low (1-20%)", "High (20%+)")) -> No Discount
A37: UT-100036 | B37: 2024-10-09 | C37: CUST_10035 | D37: New | E37: DRS-SUN-M | F37: Dresses | G37: Sundress | H37: 1999 | I37: 1 | J37: 1999 | K37: DIWALI20 | L37: 20 | M37: Wallet | N37: Mobile App | O37: Pune | P37: Maharashtra | Q37: Mumbai | R37: 2024-10-16 | S37: Delivered | T37: No | W37: Not Applicable | Y37: =B37 - WEEKDAY(B37,2) + 1 -> 2024-10-07 | Z37: =IF(R37<>"", R37-B37, "") -> 7 | AA37: =IF(L37=0, "No Discount", IF(L37<=20, "Low (1-20%)", "High (20%+)")) -> Low (1-20%)
A38: UT-100037 | B38: 2024-10-09 | C38: CUST_10036 | D38: New | E38: TOP-RFL-S | F38: Tops | G38: Ruffle Top | H38: 1799 | I38: 1 | J38: 1799 | L38: 0 | M38: UPI | N38: Instagram Shop | O38: Ahmedabad | P38: Gujarat | Q38: Mumbai | R38: 2024-10-17 | S38: Delivered | T38: Yes | U38: Changed Mind | V38: 2024-11-12 | W38: Processed | Y38: =B38 - WEEKDAY(B38,2) + 1 -> 2024-10-07 | Z38: =IF(R38<>"", R38-B38, "") -> 8 | AA38: =IF(L38=0, "No Discount", IF(L38<=20, "Low (1-20%)", "High (20%+)")) -> No Discount
A39: UT-100038 | B39: 2024-10-09 | C39: CUST_10037 | D39: Returning | E39: OUT-LTH-M | F39: Outerwear | G39: Leather Jacket | H39: 7999 | I39: 1 | J39: 7999 | L39: 0 | M39: Credit Card | N39: Website | O39: Jaipur | P39: Rajasthan | Q39: Delhi | R39: 2024-10-18 | S39: Delivered | T39: No | W39: Not Applicable | Y39: =B39 - WEEKDAY(B39,2) + 1 -> 2024-10-07 | Z39: =IF(R39<>"", R39-B39, "") -> 9 | AA39: =IF(L39=0, "No Discount", IF(L39<=20, "Low (1-20%)", "High (20%+)")) -> No Discount
A40: UT-100039 | B40: 2024-10-09 | C40: CUST_10038 | D40: New | E40: ACC-SNG-OS | F40: Accessories | G40: Sunglasses | H40: 1499 | I40: 1 | J40: 1499 | K40: FLAT10 | L40: 10 | M40: Debit Card | N40: Mobile App | O40: Lucknow | P40: Uttar Pradesh | Q40: Delhi | R40: 2024-10-17 | S40: Delivered | T40: No | W40: Not Applicable | Y40: =B40 - WEEKDAY(B40,2) + 1 -> 2024-10-07 | Z40: =IF(R40<>"", R40-B40, "") -> 8 | AA40: =IF(L40=0, "No Discount", IF(L40<=20, "Low (1-20%)", "High (20%+)")) -> Low (1-20%)
A41: UT-100040 | B41: 2024-10-10 | C41: CUST_10039 | D41: New | E41: BOT-PLZ-L | F41: Bottoms | G41: Palazzo Pants | H41: 1699 | I41: 1 | J41: 1699 | L41: 0 | M41: COD | N41: Website | O41: Bangalore | P41: Karnataka | Q41: Bangalore | R41: 2024-10-19 | S41: Delivered | T41: Yes | U41: Size Issue | V41: 2024-11-10 | W41: Processed | Y41: =B41 - WEEKDAY(B41,2) + 1 -> 2024-10-07 | Z41: =IF(R41<>"", R41-B41, "") -> 9 | AA41: =IF(L41=0, "No Discount", IF(L41<=20, "Low (1-20%)", "High (20%+)")) -> No Discount
A42: UT-100041 | B42: 2024-10-10 | C42: CUST_10040 | D42: New | E42: DRS-BDC-S | F42: Dresses | G42: Bodycon Dress | H42: 2299 | I42: 1 | J42: 2299 | L42: 0 | M42: UPI | N42: Instagram Shop | O42: Mumbai | P42: Maharashtra | Q42: Mumbai | R42: 2024-10-18 | S42: Delivered | T42: No | W42: Not Applicable | Y42: =B42 - WEEKDAY(B42,2) + 1 -> 2024-10-07 | Z42: =IF(R42<>"", R42-B42, "") -> 8 | AA42: =IF(L42=0, "No Discount", IF(L42<=20, "Low (1-20%)", "High (20%+)")) -> No Discount
A43: UT-100042 | B43: 2024-10-10 | C43: CUST_10041 | D43: Returning | E43: TOP-OFF-M | F43: Tops | G43: Off-Shoulder Top | H43: 1599 | I43: 2 | J43: 3198 | K43: DIWALI20 | L43: 20 | M43: Credit Card | N43: Mobile App | O43: Delhi | P43: Delhi | Q43: Delhi | R43: 2024-10-17 | S43: Delivered | T43: Yes | U43: Wrong Item | V43: 2024-11-08 | W43: Processed | Y43: =B43 - WEEKDAY(B43,2) + 1 -> 2024-10-07 | Z43: =IF(R43<>"", R43-B43, "") -> 7 | AA43: =IF(L43=0, "No Discount", IF(L43<=20, "Low (1-20%)", "High (20%+)")) -> Low (1-20%)
A44: UT-100043 | B44: 2024-10-10 | C44: CUST_10042 | D44: New | E44: OUT-DNM-L | F44: Outerwear | G44: Denim Vest | H44: 2499 | I44: 1 | J44: 2499 | L44: 0 | M44: Wallet | N44: Website | O44: Chandigarh | P44: Punjab | Q44: Delhi | R44: 2024-10-20 | S44: Delivered | T44: No | W44: Not Applicable | Y44: =B44 - WEEKDAY(B44,2) + 1 -> 2024-10-07 | Z44: =IF(R44<>"", R44-B44, "") -> 10 | AA44: =IF(L44=0, "No Discount", IF(L44<=20, "Low (1-20%)", "High (20%+)")) -> No Discount
A45: UT-100044 | B45: 2024-10-11 | C45: CUST_10043 | D45: New | E45: ACC-HBG-OS | F45: Accessories | G45: Hobo Bag | H45: 1899 | I45: 1 | J45: 1899 | L45: 0 | M45: Debit Card | N45: Instagram Shop | O45: Noida | P45: Uttar Pradesh | Q45: Delhi | R45: 2024-10-21 | S45: Delivered | T45: Yes | U45: Damaged in Transit | V45: 2024-11-12 | W45: Processed | Y45: =B45 - WEEKDAY(B45,2) + 1 -> 2024-10-07 | Z45: =IF(R45<>"", R45-B45, "") -> 10 | AA45: =IF(L45=0, "No Discount", IF(L45<=20, "Low (1-20%)", "High (20%+)")) -> No Discount
A46: UT-100045 | B46: 2024-10-11 | C46: CUST_10044 | D46: New | E46: BOT-CHP-M | F46: Bottoms | G46: Chino Pants | H46: 1999 | I46: 1 | J46: 1999 | K46: FIRST15 | L46: 15 | M46: UPI | N46: Mobile App | O46: Gurgaon | P46: Haryana | Q46: Delhi | R46: 2024-10-19 | S46: Delivered | T46: No | W46: Not Applicable | Y46: =B46 - WEEKDAY(B46,2) + 1 -> 2024-10-07 | Z46: =IF(R46<>"", R46-B46, "") -> 8 | AA46: =IF(L46=0, "No Discount", IF(L46<=20, "Low (1-20%)", "High (20%+)")) -> Low (1-20%)
A47: UT-100046 | B47: 2024-10-11 | C47: CUST_10045 | D47: Returning | E47: DRS-WRP-M | F47: Dresses | G47: Wrap Dress | H47: 2599 | I47: 1 | J47: 2599 | L47: 0 | M47: Credit Card | N47: Website | O47: Indore | P47: Madhya Pradesh | Q47: Mumbai | R47: 2024-10-20 | S47: Delivered | T47: No | W47: Not Applicable | Y47: =B47 - WEEKDAY(B47,2) + 1 -> 2024-10-07 | Z47: =IF(R47<>"", R47-B47, "") -> 9 | AA47: =IF(L47=0, "No Discount", IF(L47<=20, "Low (1-20%)", "High (20%+)")) -> No Discount
A48: UT-100047 | B48: 2024-10-11 | C48: CUST_10046 | D48: New | E48: TOP-STR-S | F48: Tops | G48: Striped Tee | H48: 1299 | I48: 1 | J48: 1299 | L48: 0 | M48: COD | N48: Instagram Shop | O48: Surat | P48: Gujarat | Q48: Mumbai | S48: RTO | T48: No | W48: Not Applicable | Y48: =B48 - WEEKDAY(B48,2) + 1 -> 2024-10-07 | Z48: =IF(R48<>"", R48-B48, "") | AA48: =IF(L48=0, "No Discount", IF(L48<=20, "Low (1-20%)", "High (20%+)")) -> No Discount
A49: UT-100048 | B49: 2024-10-12 | C49: CUST_10047 | D49: New | E49: OUT-PRK-XL | F49: Outerwear | G49: Parka Jacket | H49: 5999 | I49: 1 | J49: 5999 | K49: DIWALI20 | L49: 20 | M49: Credit Card | N49: Mobile App | O49: Patna | P49: Bihar | Q49: Delhi | R49: 2024-10-22 | S49: Delivered | T49: Yes | U49: Size Issue | V49: 2024-11-15 | W49: Processed | Y49: =B49 - WEEKDAY(B49,2) + 1 -> 2024-10-07 | Z49: =IF(R49<>"", R49-B49, "") -> 10 | AA49: =IF(L49=0, "No Discount", IF(L49<=20, "Low (1-20%)", "High (20%+)")) -> Low (1-20%)
A50: UT-100049 | B50: 2024-10-12 | C50: CUST_10048 | D50: New | E50: ACC-EAR-OS | F50: Accessories | G50: Hoop Earrings | H50: 799 | I50: 2 | J50: 1598 | L50: 0 | M50: UPI | N50: Website | O50: Bhopal | P50: Madhya Pradesh | Q50: Mumbai | R50: 2024-10-20 | S50: Delivered | T50: No | W50: Not Applicable | Y50: =B50 - WEEKDAY(B50,2) + 1 -> 2024-10-07 | Z50: =IF(R50<>"", R50-B50, "") -> 8 | AA50: =IF(L50=0, "No Discount", IF(L50<=20, "Low (1-20%)", "High (20%+)")) -> No Discount
A51: UT-100050 | B51: 2024-10-12 | C51: CUST_10049 | D51: Returning | E51: BOT-LGN-S | F51: Bottoms | G51: Leggings | H51: 999 | I51: 2 | J51: 1998 | L51: 0 | M51: Wallet | N51: Mobile App | O51: Nagpur | P51: Maharashtra | Q51: Mumbai | R51: 2024-10-19 | S51: Delivered | T51: No | W51: Not Applicable | Y51: =B51 - WEEKDAY(B51,2) + 1 -> 2024-10-07 | Z51: =IF(R51<>"", R51-B51, "") -> 7 | AA51: =IF(L51=0, "No Discount", IF(L51<=20, "Low (1-20%)", "High (20%+)")) -> No Discount
A52: UT-100051 | B52: 2024-10-12 | C52: CUST_10050 | D52: New | E52: DRS-CTN-L | F52: Dresses | G52: Cotton Dress | H52: 1899 | I52: 1 | J52: 1899 | L52: 0 | M52: Debit Card | N52: Instagram Shop | O52: Coimbatore | P52: Tamil Nadu | Q52: Bangalore | R52: 2024-10-22 | S52: Delivered | T52: Yes | U52: Quality Defect | V52: 2024-11-14 | W52: Processed | Y52: =B52 - WEEKDAY(B52,2) + 1 -> 2024-10-07 | Z52: =IF(R52<>"", R52-B52, "") -> 10 | AA52: =IF(L52=0, "No Discount", IF(L52<=20, "Low (1-20%)", "High (20%+)")) -> No Discount
A53: UT-100052 | B53: 2024-10-13 | C53: CUST_10051 | D53: New | E53: TOP-LCE-M | F53: Tops | G53: Lace Top | H53: 1699 | I53: 1 | J53: 1699 | K53: FLAT10 | L53: 10 | M53: Credit Card | N53: Website | O53: Kochi | P53: Kerala | Q53: Bangalore | R53: 2024-10-21 | S53: Delivered | T53: No | W53: Not Applicable | Y53: =B53 - WEEKDAY(B53,2) + 1 -> 2024-10-07 | Z53: =IF(R53<>"", R53-B53, "") -> 8 | AA53: =IF(L53=0, "No Discount", IF(L53<=20, "Low (1-20%)", "High (20%+)")) -> Low (1-20%)
A54: UT-100053 | B54: 2024-10-13 | C54: CUST_10052 | D54: New | E54: OUT-BOM-M | F54: Outerwear | G54: Bomber Jacket | H54: 3799 | I54: 1 | J54: 3799 | L54: 0 | M54: UPI | N54: Mobile App | O54: Vizag | P54: Andhra Pradesh | Q54: Bangalore | R54: 2024-10-23 | S54: Delivered | T54: Yes | U54: Size Issue | V54: 2024-11-18 | W54: Processed | Y54: =B54 - WEEKDAY(B54,2) + 1 -> 2024-10-07 | Z54: =IF(R54<>"", R54-B54, "") -> 10 | AA54: =IF(L54=0, "No Discount", IF(L54<=20, "Low (1-20%)", "High (20%+)")) -> No Discount
A55: UT-100054 | B55: 2024-10-13 | C55: CUST_10053 | D55: Returning | E55: ACC-NCK-OS | F55: Accessories | G55: Pendant Necklace | H55: 1299 | I55: 1 | J55: 1299 | L55: 0 | M55: COD | N55: Instagram Shop | O55: Thiruvananthapuram | P55: Kerala | Q55: Bangalore | R55: 2024-10-22 | S55: Delivered | T55: No | W55: Not Applicable | Y55: =B55 - WEEKDAY(B55,2) + 1 -> 2024-10-07 | Z55: =IF(R55<>"", R55-B55, "") -> 9 | AA55: =IF(L55=0, "No Discount", IF(L55<=20, "Low (1-20%)", "High (20%+)")) -> No Discount
A56: UT-100055 | B56: 2024-10-13 | C56: CUST_10054 | D56: New | E56: BOT-WID-M | F56: Bottoms | G56: Wide Leg Pants | H56: 2099 | I56: 1 | J56: 2099 | K56: DIWALI20 | L56: 20 | M56: Credit Card | N56: Website | O56: Mysore | P56: Karnataka | Q56: Bangalore | R56: 2024-10-24 | S56: Delivered | T56: No | W56: Not Applicable | Y56: =B56 - WEEKDAY(B56,2) + 1 -> 2024-10-07 | Z56: =IF(R56<>"", R56-B56, "") -> 11 | AA56: =IF(L56=0, "No Discount", IF(L56<=20, "Low (1-20%)", "High (20%+)")) -> Low (1-20%)
A57: UT-100056 | B57: 2024-10-14 | C57: CUST_10055 | D57: New | E57: DRS-TIR-S | F57: Dresses | G57: Tiered Dress | H57: 2799 | I57: 1 | J57: 2799 | L57: 0 | M57: Debit Card | N57: Mobile App | O57: Vadodara | P57: Gujarat | Q57: Mumbai | R57: 2024-10-23 | S57: Delivered | T57: Yes | U57: Changed Mind | V57: 2024-11-16 | W57: Processed | Y57: =B57 - WEEKDAY(B57,2) + 1 -> 2024-10-14 | Z57: =IF(R57<>"", R57-B57, "") -> 9 | AA57: =IF(L57=0, "No Discount", IF(L57<=20, "Low (1-20%)", "High (20%+)")) -> No Discount
A58: UT-100057 | B58: 2024-10-14 | C58: CUST_10056 | D58: New | E58: TOP-PEP-M | F58: Tops | G58: Peplum Top | H58: 1499 | I58: 1 | J58: 1499 | L58: 0 | M58: Wallet | N58: Website | O58: Rajkot | P58: Gujarat | Q58: Mumbai | R58: 2024-10-22 | S58: Delivered | T58: No | W58: Not Applicable | Y58: =B58 - WEEKDAY(B58,2) + 1 -> 2024-10-14 | Z58: =IF(R58<>"", R58-B58, "") -> 8 | AA58: =IF(L58=0, "No Discount", IF(L58<=20, "Low (1-20%)", "High (20%+)")) -> No Discount
A59: UT-100058 | B59: 2024-10-14 | C59: CUST_10057 | D59: Returning | E59: OUT-QTD-L | F59: Outerwear | G59: Quilted Jacket | H59: 4499 | I59: 1 | J59: 4499 | K59: FIRST15 | L59: 15 | M59: UPI | N59: Instagram Shop | O59: Kanpur | P59: Uttar Pradesh | Q59: Delhi | R59: 2024-10-25 | S59: Delivered | T59: Yes | U59: Wrong Item | V59: 2024-11-20 | W59: Processed | Y59: =B59 - WEEKDAY(B59,2) + 1 -> 2024-10-14 | Z59: =IF(R59<>"", R59-B59, "") -> 11 | AA59: =IF(L59=0, "No Discount", IF(L59<=20, "Low (1-20%)", "High (20%+)")) -> Low (1-20%)
A60: UT-100059 | B60: 2024-10-14 | C60: CUST_10058 | D60: New | E60: ACC-BRC-OS | F60: Accessories | G60: Charm Bracelet | H60: 899 | I60: 1 | J60: 899 | L60: 0 | M60: Credit Card | N60: Mobile App | O60: Mumbai | P60: Maharashtra | Q60: Mumbai | R60: 2024-10-23 | S60: Delivered | T60: No | W60: Not Applicable | Y60: =B60 - WEEKDAY(B60,2) + 1 -> 2024-10-14 | Z60: =IF(R60<>"", R60-B60, "") -> 9 | AA60: =IF(L60=0, "No Discount", IF(L60<=20, "Low (1-20%)", "High (20%+)")) -> No Discount
A61: UT-100060 | B61: 2024-10-15 | C61: CUST_10059 | D61: New | E61: BOT-CRP-S | F61: Bottoms | G61: Cropped Pants | H61: 1799 | I61: 1 | J61: 1799 | L61: 0 | M61: COD | N61: Website | O61: Delhi | P61: Delhi | Q61: Delhi | S61: RTO | T61: No | W61: Not Applicable | Y61: =B61 - WEEKDAY(B61,2) + 1 -> 2024-10-14 | Z61: =IF(R61<>"", R61-B61, "") | AA61: =IF(L61=0, "No Discount", IF(L61<=20, "Low (1-20%)", "High (20%+)")) -> No Discount
A62: UT-100061 | B62: 2024-10-15 | C62: CUST_10060 | D62: New | E62: DRS-SLP-M | F62: Dresses | G62: Slip Dress | H62: 2199 | I62: 1 | J62: 2199 | K62: DIWALI20 | L62: 20 | M62: Debit Card | N62: Instagram Shop | O62: Kolkata | P62: West Bengal | Q62: Delhi | R62: 2024-10-26 | S62: Delivered | T62: Yes | U62: Size Issue | V62: 2024-11-22 | W62: Processed | Y62: =B62 - WEEKDAY(B62,2) + 1 -> 2024-10-14 | Z62: =IF(R62<>"", R62-B62, "") -> 11 | AA62: =IF(L62=0, "No Discount", IF(L62<=20, "Low (1-20%)", "High (20%+)")) -> Low (1-20%)
A63: UT-100062 | B63: 2024-10-15 | C63: CUST_10061 | D63: Returning | E63: TOP-HLT-L | F63: Tops | G63: Halter Top | H63: 1399 | I63: 1 | J63: 1399 | L63: 0 | M63: UPI | N63: Mobile App | O63: Chennai | P63: Tamil Nadu | Q63: Bangalore | R63: 2024-10-24 | S63: Delivered | T63: No | W63: Not Applicable | Y63: =B63 - WEEKDAY(B63,2) + 1 -> 2024-10-14 | Z63: =IF(R63<>"", R63-B63, "") -> 9 | AA63: =IF(L63=0, "No Discount", IF(L63<=20, "Low (1-20%)", "High (20%+)")) -> No Discount
A64: UT-100063 | B64: 2024-10-15 | C64: CUST_10062 | D64: New | E64: OUT-FLC-M | F64: Outerwear | G64: Fleece Jacket | H64: 2999 | I64: 1 | J64: 2999 | L64: 0 | M64: Credit Card | N64: Website | O64: Hyderabad | P64: Telangana | Q64: Bangalore | R64: 2024-10-27 | S64: Delivered | T64: Yes | U64: Quality Defect | V64: 2024-11-24 | W64: Processed | Y64: =B64 - WEEKDAY(B64,2) + 1 -> 2024-10-14 | Z64: =IF(R64<>"", R64-B64, "") -> 12 | AA64: =IF(L64=0, "No Discount", IF(L64<=20, "Low (1-20%)", "High (20%+)")) -> No Discount
A65: UT-100064 | B65: 2024-10-16 | C65: CUST_10063 | D65: New | E65: ACC-RNG-OS | F65: Accessories | G65: Cocktail Ring | H65: 699 | I65: 2 | J65: 1398 | K65: FLAT10 | L65: 10 | M65: Wallet | N65: Instagram Shop | O65: Pune | P65: Maharashtra | Q65: Mumbai | R65: 2024-10-25 | S65: Delivered | T65: No | W65: Not Applicable | Y65: =B65 - WEEKDAY(B65,2) + 1 -> 2024-10-14 | Z65: =IF(R65<>"", R65-B65, "") -> 9 | AA65: =IF(L65=0, "No Discount", IF(L65<=20, "Low (1-20%)", "High (20%+)")) -> Low (1-20%)
A66: UT-100065 | B66: 2024-10-16 | C66: CUST_10064 | D66: New | E66: BOT-SKN-M | F66: Bottoms | G66: Skinny Jeans | H66: 2199 | I66: 1 | J66: 2199 | L66: 0 | M66: COD | N66: Mobile App | O66: Ahmedabad | P66: Gujarat | Q66: Mumbai | R66: 2024-10-28 | S66: Delivered | T66: Yes | U66: Size Issue | V66: 2024-11-25 | W66: Processed | Y66: =B66 - WEEKDAY(B66,2) + 1 -> 2024-10-14 | Z66: =IF(R66<>"", R66-B66, "") -> 12 | AA66: =IF(L66=0, "No Discount", IF(L66<=20, "Low (1-20%)", "High (20%+)")) -> No Discount
A67: UT-100066 | B67: 2024-10-16 | C67: CUST_10065 | D67: Returning | E67: DRS-KNT-S | F67: Dresses | G67: Knit Dress | H67: 2499 | I67: 1 | J67: 2499 | L67: 0 | M67: Credit Card | N67: Website | O67: Jaipur | P67: Rajasthan | Q67: Delhi | R67: 2024-10-26 | S67: Delivered | T67: No | W67: Not Applicable | Y67: =B67 - WEEKDAY(B67,2) + 1 -> 2024-10-14 | Z67: =IF(R67<>"", R67-B67, "") -> 10 | AA67: =IF(L67=0, "No Discount", IF(L67<=20, "Low (1-20%)", "High (20%+)")) -> No Discount
A68: UT-100067 | B68: 2024-10-16 | C68: CUST_10066 | D68: New | E68: TOP-EMB-M | F68: Tops | G68: Embroidered Top | H68: 1899 | I68: 1 | J68: 1899 | K68: DIWALI20 | L68: 20 | M68: UPI | N68: Instagram Shop | O68: Lucknow | P68: Uttar Pradesh | Q68: Delhi | R68: 2024-10-27 | S68: Delivered | T68: Yes | U68: Changed Mind | V68: 2024-11-20 | W68: Processed | Y68: =B68 - WEEKDAY(B68,2) + 1 -> 2024-10-14 | Z68: =IF(R68<>"", R68-B68, "") -> 11 | AA68: =IF(L68=0, "No Discount", IF(L68<=20, "Low (1-20%)", "High (20%+)")) -> Low (1-20%)
A69: UT-100068 | B69: 2024-10-17 | C69: CUST_10067 | D69: New | E69: OUT-SHR-L | F69: Outerwear | G69: Shrug | H69: 1299 | I69: 1 | J69: 1299 | L69: 0 | M69: Debit Card | N69: Mobile App | O69: Bangalore | P69: Karnataka | Q69: Bangalore | R69: 2024-10-28 | S69: Delivered | T69: No | W69: Not Applicable | Y69: =B69 - WEEKDAY(B69,2) + 1 -> 2024-10-14 | Z69: =IF(R69<>"", R69-B69, "") -> 11 | AA69: =IF(L69=0, "No Discount", IF(L69<=20, "Low (1-20%)", "High (20%+)")) -> No Discount
A70: UT-100069 | B70: 2024-10-17 | C70: CUST_10068 | D70: New | E70: ACC-CLT-OS | F70: Accessories | G70: Clutch Bag | H70: 1599 | I70: 1 | J70: 1599 | L70: 0 | M70: Credit Card | N70: Website | O70: Mumbai | P70: Maharashtra | Q70: Mumbai | R70: 2024-10-27 | S70: Delivered | T70: Yes | U70: Damaged in Transit | V70: 2024-11-22 | W70: Processed | Y70: =B70 - WEEKDAY(B70,2) + 1 -> 2024-10-14 | Z70: =IF(R70<>"", R70-B70, "") -> 10 | AA70: =IF(L70=0, "No Discount", IF(L70<=20, "Low (1-20%)", "High (20%+)")) -> No Discount
A71: UT-100070 | B71: 2024-10-17 | C71: CUST_10069 | D71: Returning | E71: BOT-FLR-S | F71: Bottoms | G71: Flared Jeans | H71: 2099 | I71: 1 | J71: 2099 | K71: FIRST15 | L71: 15 | M71: UPI | N71: Instagram Shop | O71: Delhi | P71: Delhi | Q71: Delhi | R71: 2024-10-29 | S71: Delivered | T71: No | W71: Not Applicable | Y71: =B71 - WEEKDAY(B71,2) + 1 -> 2024-10-14 | Z71: =IF(R71<>"", R71-B71, "") -> 12 | AA71: =IF(L71=0, "No Discount", IF(L71<=20, "Low (1-20%)", "High (20%+)")) -> Low (1-20%)
A72: UT-100071 | B72: 2024-10-17 | C72: CUST_10070 | D72: New | E72: DRS-PIN-M | F72: Dresses | G72: Pinafore Dress | H72: 2299 | I72: 1 | J72: 2299 | L72: 0 | M72: COD | N72: Mobile App | O72: Chandigarh | P72: Punjab | Q72: Delhi | S72: RTO | T72: No | W72: Not Applicable | Y72: =B72 - WEEKDAY(B72,2) + 1 -> 2024-10-14 | Z72: =IF(R72<>"", R72-B72, "") | AA72: =IF(L72=0, "No Discount", IF(L72<=20, "Low (1-20%)", "High (20%+)")) -> No Discount
A73: UT-100072 | B73: 2024-10-18 | C73: CUST_10071 | D73: New | E73: TOP-CRW-L | F73: Tops | G73: Crew Neck Tee | H73: 1199 | I73: 2 | J73: 2398 | L73: 0 | M73: Wallet | N73: Website | O73: Noida | P73: Uttar Pradesh | Q73: Delhi | R73: 2024-10-28 | S73: Delivered | T73: No | W73: Not Applicable | Y73: =B73 - WEEKDAY(B73,2) + 1 -> 2024-10-14 | Z73: =IF(R73<>"", R73-B73, "") -> 10 | AA73: =IF(L73=0, "No Discount", IF(L73<=20, "Low (1-20%)", "High (20%+)")) -> No Discount
A74: UT-100073 | B74: 2024-10-18 | C74: CUST_10072 | D74: New | E74: OUT-CDG-M | F74: Outerwear | G74: Cardigan | H74: 2599 | I74: 1 | J74: 2599 | K74: DIWALI20 | L74: 20 | M74: Credit Card | N74: Instagram Shop | O74: Gurgaon | P74: Haryana | Q74: Delhi | R74: 2024-10-30 | S74: Delivered | T74: Yes | U74: Size Issue | V74: 2024-11-26 | W74: Processed | Y74: =B74 - WEEKDAY(B74,2) + 1 -> 2024-10-14 | Z74: =IF(R74<>"", R74-B74, "") -> 12 | AA74: =IF(L74=0, "No Discount", IF(L74<=20, "Low (1-20%)", "High (20%+)")) -> Low (1-20%)
A75: UT-100074 | B75: 2024-10-18 | C75: CUST_10073 | D75: Returning | E75: ACC-SCR-OS | F75: Accessories | G75: Hair Scrunchie | H75: 299 | I75: 5 | J75: 1495 | L75: 0 | M75: UPI | N75: Mobile App | O75: Indore | P75: Madhya Pradesh | Q75: Mumbai | R75: 2024-10-27 | S75: Delivered | T75: No | W75: Not Applicable | Y75: =B75 - WEEKDAY(B75,2) + 1 -> 2024-10-14 | Z75: =IF(R75<>"", R75-B75, "") -> 9 | AA75: =IF(L75=0, "No Discount", IF(L75<=20, "Low (1-20%)", "High (20%+)")) -> No Discount
A76: UT-100075 | B76: 2024-10-18 | C76: CUST_10074 | D76: New | E76: BOT-PPR-M | F76: Bottoms | G76: Paper Bag Pants | H76: 1899 | I76: 1 | J76: 1899 | L76: 0 | M76: Debit Card | N76: Website | O76: Surat | P76: Gujarat | Q76: Mumbai | R76: 2024-10-30 | S76: Delivered | T76: Yes | U76: Wrong Item | V76: 2024-11-28 | W76: Processed | Y76: =B76 - WEEKDAY(B76,2) + 1 -> 2024-10-14 | Z76: =IF(R76<>"", R76-B76, "") -> 12 | AA76: =IF(L76=0, "No Discount", IF(L76<=20, "Low (1-20%)", "High (20%+)")) -> No Discount
A77: UT-100076 | B77: 2024-10-19 | C77: CUST_10075 | D77: New | E77: DRS-SMK-S | F77: Dresses | G77: Smocked Dress | H77: 2199 | I77: 1 | J77: 2199 | L77: 0 | M77: Credit Card | N77: Instagram Shop | O77: Patna | P77: Bihar | Q77: Delhi | R77: 2024-10-31 | S77: Delivered | T77: No | W77: Not Applicable | Y77: =B77 - WEEKDAY(B77,2) + 1 -> 2024-10-14 | Z77: =IF(R77<>"", R77-B77, "") -> 12 | AA77: =IF(L77=0, "No Discount", IF(L77<=20, "Low (1-20%)", "High (20%+)")) -> No Discount
A78: UT-100077 | B78: 2024-10-19 | C78: CUST_10076 | D78: New | E78: TOP-BTN-M | F78: Tops | G78: Button-Down Shirt | H78: 1799 | I78: 1 | J78: 1799 | K78: FLAT10 | L78: 10 | M78: COD | N78: Mobile App | O78: Bhopal | P78: Madhya Pradesh | Q78: Mumbai | R78: 2024-10-29 | S78: Delivered | T78: Yes | U78: Quality Defect | V78: 2024-11-25 | W78: Processed | Y78: =B78 - WEEKDAY(B78,2) + 1 -> 2024-10-14 | Z78: =IF(R78<>"", R78-B78, "") -> 10 | AA78: =IF(L78=0, "No Discount", IF(L78<=20, "Low (1-20%)", "High (20%+)")) -> Low (1-20%)
A79: UT-100078 | B79: 2024-10-19 | C79: CUST_10077 | D79: Returning | E79: OUT-VLV-L | F79: Outerwear | G79: Velvet Blazer | H79: 4999 | I79: 1 | J79: 4999 | L79: 0 | M79: UPI | N79: Website | O79: Nagpur | P79: Maharashtra | Q79: Mumbai | R79: 2024-11-01 | S79: Delivered | T79: No | W79: Not Applicable | Y79: =B79 - WEEKDAY(B79,2) + 1 -> 2024-10-14 | Z79: =IF(R79<>"", R79-B79, "") -> 13 | AA79: =IF(L79=0, "No Discount", IF(L79<=20, "Low (1-20%)", "High (20%+)")) -> No Discount
A80: UT-100079 | B80: 2024-10-19 | C80: CUST_10078 | D80: New | E80: ACC-TOT-OS | F80: Accessories | G80: Canvas Tote | H80: 999 | I80: 1 | J80: 999 | L80: 0 | M80: Wallet | N80: Instagram Shop | O80: Coimbatore | P80: Tamil Nadu | Q80: Bangalore | R80: 2024-10-30 | S80: Delivered | T80: Yes | U80: Size Issue | V80: 2024-11-28 | W80: Processed | Y80: =B80 - WEEKDAY(B80,2) + 1 -> 2024-10-14 | Z80: =IF(R80<>"", R80-B80, "") -> 11 | AA80: =IF(L80=0, "No Discount", IF(L80<=20, "Low (1-20%)", "High (20%+)")) -> No Discount
A81: UT-100080 | B81: 2024-10-20 | C81: CUST_10079 | D81: New | E81: BOT-CRG-S | F81: Bottoms | G81: Cargo Shorts | H81: 1499 | I81: 1 | J81: 1499 | K81: DIWALI20 | L81: 20 | M81: Credit Card | N81: Mobile App | O81: Kochi | P81: Kerala | Q81: Bangalore | R81: 2024-10-31 | S81: Delivered | T81: No | W81: Not Applicable | Y81: =B81 - WEEKDAY(B81,2) + 1 -> 2024-10-14 | Z81: =IF(R81<>"", R81-B81, "") -> 11 | AA81: =IF(L81=0, "No Discount", IF(L81<=20, "Low (1-20%)", "High (20%+)")) -> Low (1-20%)
A82: UT-100081 | B82: 2024-10-20 | C82: CUST_10080 | D82: New | E82: DRS-BTR-M | F82: Dresses | G82: Butterfly Dress | H82: 2899 | I82: 1 | J82: 2899 | L82: 0 | M82: Debit Card | N82: Website | O82: Vizag | P82: Andhra Pradesh | Q82: Bangalore | R82: 2024-11-02 | S82: Delivered | T82: Yes | U82: Changed Mind | V82: 2024-11-30 | W82: Processed | Y82: =B82 - WEEKDAY(B82,2) + 1 -> 2024-10-14 | Z82: =IF(R82<>"", R82-B82, "") -> 13 | AA82: =IF(L82=0, "No Discount", IF(L82<=20, "Low (1-20%)", "High (20%+)")) -> No Discount
A83: UT-100082 | B83: 2024-10-20 | C83: CUST_10081 | D83: Returning | E83: TOP-VNK-L | F83: Tops | G83: V-Neck Tee | H83: 1099 | I83: 2 | J83: 2198 | L83: 0 | M83: UPI | N83: Instagram Shop | O83: Thiruvananthapuram | P83: Kerala | Q83: Bangalore | R83: 2024-10-30 | S83: Delivered | T83: No | W83: Not Applicable | Y83: =B83 - WEEKDAY(B83,2) + 1 -> 2024-10-14 | Z83: =IF(R83<>"", R83-B83, "") -> 10 | AA83: =IF(L83=0, "No Discount", IF(L83<=20, "Low (1-20%)", "High (20%+)")) -> No Discount
A84: UT-100083 | B84: 2024-10-20 | C84: CUST_10082 | D84: New | E84: OUT-TRN-M | F84: Outerwear | G84: Trench Coat | H84: 5499 | I84: 1 | J84: 5499 | K84: FIRST15 | L84: 15 | M84: Credit Card | N84: Mobile App | O84: Mysore | P84: Karnataka | Q84: Bangalore | R84: 2024-11-03 | S84: Delivered | T84: Yes | U84: Size Issue | V84: 2024-12-01 | W84: Processed | Y84: =B84 - WEEKDAY(B84,2) + 1 -> 2024-10-14 | Z84: =IF(R84<>"", R84-B84, "") -> 14 | AA84: =IF(L84=0, "No Discount", IF(L84<=20, "Low (1-20%)", "High (20%+)")) -> Low (1-20%)
A85: UT-100084 | B85: 2024-10-21 | C85: CUST_10083 | D85: New | E85: ACC-BDY-OS | F85: Accessories | G85: Body Chain | H85: 799 | I85: 1 | J85: 799 | L85: 0 | M85: COD | N85: Website | O85: Vadodara | P85: Gujarat | Q85: Mumbai | S85: RTO | T85: No | W85: Not Applicable | Y85: =B85 - WEEKDAY(B85,2) + 1 -> 2024-10-21 | Z85: =IF(R85<>"", R85-B85, "") | AA85: =IF(L85=0, "No Discount", IF(L85<=20, "Low (1-20%)", "High (20%+)")) -> No Discount
A86: UT-100085 | B86: 2024-10-21 | C86: CUST_10084 | D86: New | E86: BOT-JGR-L | F86: Bottoms | G86: Jogger Pants | H86: 1599 | I86: 1 | J86: 1599 | L86: 0 | M86: Wallet | N86: Instagram Shop | O86: Rajkot | P86: Gujarat | Q86: Mumbai | R86: 2024-11-02 | S86: Delivered | T86: No | W86: Not Applicable | Y86: =B86 - WEEKDAY(B86,2) + 1 -> 2024-10-21 | Z86: =IF(R86<>"", R86-B86, "") -> 12 | AA86: =IF(L86=0, "No Discount", IF(L86<=20, "Low (1-20%)", "High (20%+)")) -> No Discount
A87: UT-100086 | B87: 2024-10-21 | C87: CUST_10085 | D87: Returning | E87: DRS-RFL-S | F87: Dresses | G87: Ruffle Dress | H87: 2699 | I87: 1 | J87: 2699 | K87: DIWALI20 | L87: 20 | M87: Credit Card | N87: Mobile App | O87: Kanpur | P87: Uttar Pradesh | Q87: Delhi | R87: 2024-11-01 | S87: Delivered | T87: Yes | U87: Quality Defect | V87: 2024-11-30 | W87: Processed | Y87: =B87 - WEEKDAY(B87,2) + 1 -> 2024-10-21 | Z87: =IF(R87<>"", R87-B87, "") -> 11 | AA87: =IF(L87=0, "No Discount", IF(L87<=20, "Low (1-20%)", "High (20%+)")) -> Low (1-20%)
A88: UT-100087 | B88: 2024-10-21 | C88: CUST_10086 | D88: New | E88: TOP-SQR-M | F88: Tops | G88: Square Neck Top | H88: 1499 | I88: 1 | J88: 1499 | L88: 0 | M88: UPI | N88: Website | O88: Mumbai | P88: Maharashtra | Q88: Mumbai | R88: 2024-11-02 | S88: Delivered | T88: No | W88: Not Applicable | Y88: =B88 - WEEKDAY(B88,2) + 1 -> 2024-10-21 | Z88: =IF(R88<>"", R88-B88, "") -> 12 | AA88: =IF(L88=0, "No Discount", IF(L88<=20, "Low (1-20%)", "High (20%+)")) -> No Discount
A89: UT-100088 | B89: 2024-10-22 | C89: CUST_10087 | D89: New | E89: OUT-WND-L | F89: Outerwear | G89: Windbreaker | H89: 3299 | I89: 1 | J89: 3299 | L89: 0 | M89: Debit Card | N89: Instagram Shop | O89: Delhi | P89: Delhi | Q89: Delhi | R89: 2024-11-04 | S89: Delivered | T89: Yes | U89: Wrong Item | V89: 2024-12-03 | W89: Processed | Y89: =B89 - WEEKDAY(B89,2) + 1 -> 2024-10-21 | Z89: =IF(R89<>"", R89-B89, "") -> 13 | AA89: =IF(L89=0, "No Discount", IF(L89<=20, "Low (1-20%)", "High (20%+)")) -> No Discount
A90: UT-100089 | B90: 2024-10-22 | C90: CUST_10088 | D90: New | E90: ACC-ANK-OS | F90: Accessories | G90: Anklet | H90: 499 | I90: 2 | J90: 998 | K90: FLAT10 | L90: 10 | M90: Credit Card | N90: Mobile App | O90: Kolkata | P90: West Bengal | Q90: Delhi | R90: 2024-11-01 | S90: Delivered | T90: No | W90: Not Applicable | Y90: =B90 - WEEKDAY(B90,2) + 1 -> 2024-10-21 | Z90: =IF(R90<>"", R90-B90, "") -> 10 | AA90: =IF(L90=0, "No Discount", IF(L90<=20, "Low (1-20%)", "High (20%+)")) -> Low (1-20%)
A91: UT-100090 | B91: 2024-10-22 | C91: CUST_10089 | D91: Returning | E91: BOT-TRS-M | F91: Bottoms | G91: Tailored Trousers | H91: 2399 | I91: 1 | J91: 2399 | L91: 0 | M91: UPI | N91: Website | O91: Chennai | P91: Tamil Nadu | Q91: Bangalore | R91: 2024-11-03 | S91: Delivered | T91: No | W91: Not Applicable | Y91: =B91 - WEEKDAY(B91,2) + 1 -> 2024-10-21 | Z91: =IF(R91<>"", R91-B91, "") -> 12 | AA91: =IF(L91=0, "No Discount", IF(L91<=20, "Low (1-20%)", "High (20%+)")) -> No Discount
A92: UT-100091 | B92: 2024-10-22 | C92: CUST_10090 | D92: New | E92: DRS-LST-M | F92: Dresses | G92: Lace Trim Dress | H92: 2599 | I92: 1 | J92: 2599 | L92: 0 | M92: COD | N92: Instagram Shop | O92: Hyderabad | P92: Telangana | Q92: Bangalore | S92: RTO | T92: No | W92: Not Applicable | Y92: =B92 - WEEKDAY(B92,2) + 1 -> 2024-10-21 | Z92: =IF(R92<>"", R92-B92, "") | AA92: =IF(L92=0, "No Discount", IF(L92<=20, "Low (1-20%)", "High (20%+)")) -> No Discount
A93: UT-100092 | B93: 2024-10-23 | C93: CUST_10091 | D93: New | E93: TOP-TIE-S | F93: Tops | G93: Tie-Front Top | H93: 1399 | I93: 1 | J93: 1399 | K93: DIWALI20 | L93: 20 | M93: Wallet | N93: Mobile App | O93: Pune | P93: Maharashtra | Q93: Mumbai | R93: 2024-11-03 | S93: Delivered | T93: Yes | U93: Size Issue | V93: 2024-12-02 | W93: Processed | Y93: =B93 - WEEKDAY(B93,2) + 1 -> 2024-10-21 | Z93: =IF(R93<>"", R93-B93, "") -> 11 | AA93: =IF(L93=0, "No Discount", IF(L93<=20, "Low (1-20%)", "High (20%+)")) -> Low (1-20%)
A94: UT-100093 | B94: 2024-10-23 | C94: CUST_10092 | D94: New | E94: OUT-PUF-M | F94: Outerwear | G94: Puffer Jacket | H94: 4299 | I94: 1 | J94: 4299 | L94: 0 | M94: Credit Card | N94: Website | O94: Ahmedabad | P94: Gujarat | Q94: Mumbai | R94: 2024-11-05 | S94: Delivered | T94: No | W94: Not Applicable | Y94: =B94 - WEEKDAY(B94,2) + 1 -> 2024-10-21 | Z94: =IF(R94<>"", R94-B94, "") -> 13 | AA94: =IF(L94=0, "No Discount", IF(L94<=20, "Low (1-20%)", "High (20%+)")) -> No Discount
A95: UT-100094 | B95: 2024-10-23 | C95: CUST_10093 | D95: Returning | E95: ACC-HDR-OS | F95: Accessories | G95: Hairband | H95: 399 | I95: 3 | J95: 1197 | L95: 0 | M95: UPI | N95: Instagram Shop | O95: Jaipur | P95: Rajasthan | Q95: Delhi | R95: 2024-11-02 | S95: Delivered | T95: No | W95: Not Applicable | Y95: =B95 - WEEKDAY(B95,2) + 1 -> 2024-10-21 | Z95: =IF(R95<>"", R95-B95, "") -> 10 | AA95: =IF(L95=0, "No Discount", IF(L95<=20, "Low (1-20%)", "High (20%+)")) -> No Discount
A96: UT-100095 | B96: 2024-10-23 | C96: CUST_10094 | D96: New | E96: BOT-PLT-L | F96: Bottoms | G96: Pleated Trousers | H96: 2199 | I96: 1 | J96: 2199 | K96: FIRST15 | L96: 15 | M96: Debit Card | N96: Mobile App | O96: Lucknow | P96: Uttar Pradesh | Q96: Delhi | R96: 2024-11-05 | S96: Delivered | T96: Yes | U96: Damaged in Transit | V96: 2024-12-05 | W96: Processed | Y96: =B96 - WEEKDAY(B96,2) + 1 -> 2024-10-21 | Z96: =IF(R96<>"", R96-B96, "") -> 13 | AA96: =IF(L96=0, "No Discount", IF(L96<=20, "Low (1-20%)", "High (20%+)")) -> Low (1-20%)
A97: UT-100096 | B97: 2024-10-24 | C97: CUST_10095 | D97: New | E97: DRS-SHR-S | F97: Dresses | G97: Shirtdress | H97: 2399 | I97: 1 | J97: 2399 | L97: 0 | M97: Credit Card | N97: Website | O97: Bangalore | P97: Karnataka | Q97: Bangalore | R97: 2024-11-04 | S97: Delivered | T97: No | W97: Not Applicable | Y97: =B97 - WEEKDAY(B97,2) + 1 -> 2024-10-21 | Z97: =IF(R97<>"", R97-B97, "") -> 11 | AA97: =IF(L97=0, "No Discount", IF(L97<=20, "Low (1-20%)", "High (20%+)")) -> No Discount
A98: UT-100097 | B98: 2024-10-24 | C98: CUST_10096 | D98: New | E98: TOP-GRF-M | F98: Tops | G98: Graphic Tee | H98: 1299 | I98: 1 | J98: 1299 | L98: 0 | M98: COD | N98: Instagram Shop | O98: Mumbai | P98: Maharashtra | Q98: Mumbai | R98: 2024-11-06 | S98: Delivered | T98: Yes | U98: Changed Mind | V98: 2024-12-05 | W98: Processed | Y98: =B98 - WEEKDAY(B98,2) + 1 -> 2024-10-21 | Z98: =IF(R98<>"", R98-B98, "") -> 13 | AA98: =IF(L98=0, "No Discount", IF(L98<=20, "Low (1-20%)", "High (20%+)")) -> No Discount
A99: UT-100098 | B99: 2024-10-24 | C99: CUST_10097 | D99: Returning | E99: OUT-SHW-L | F99: Outerwear | G99: Shawl Wrap | H99: 2799 | I99: 1 | J99: 2799 | K99: DIWALI20 | L99: 20 | M99: UPI | N99: Mobile App | O99: Delhi | P99: Delhi | Q99: Delhi | R99: 2024-11-05 | S99: Delivered | T99: No | W99: Not Applicable | Y99: =B99 - WEEKDAY(B99,2) + 1 -> 2024-10-21 | Z99: =IF(R99<>"", R99-B99, "") -> 12 | AA99: =IF(L99=0, "No Discount", IF(L99<=20, "Low (1-20%)", "High (20%+)")) -> Low (1-20%)
A100: UT-100099 | B100: 2024-10-24 | C100: CUST_10098 | D100: New | E100: ACC-BLT-S | F100: Accessories | G100: Braided Belt | H100: 699 | I100: 1 | J100: 699 | L100: 0 | M100: Wallet | N100: Website | O100: Chandigarh | P100: Punjab | Q100: Delhi | R100: 2024-11-04 | S100: Delivered | T100: No | W100: Not Applicable | Y100: =B100 - WEEKDAY(B100,2) + 1 -> 2024-10-21 | Z100: =IF(R100<>"", R100-B100, "") -> 11 | AA100: =IF(L100=0, "No Discount", IF(L100<=20, "Low (1-20%)", "High (20%+)")) -> No Discount
...

Sheet Trend_Analysis
A1: Week Start | B1: Orders | C1: Return Rate | D1: Avg Discount% | E1: Delivered_Orders | F1: Returned Orders
A2: =MIN(Working_Data!Y:Y) -> 2024-09-30 | B2: =COUNTIF(Working_Data!Y:Y, A2) -> 27 | C2: =COUNTIFS(Working_Data!Y:Y, A2, Working_Data!S:S, "*Delivered*") -> 24 | D2: =AVERAGEIF(Working_Data!$Y:$Y, A2, Working_Data!$L:$L) -> 5.1851852 | E2: =COUNTIFS(Working_Data!$Y:$Y, A2, Working_Data!$S:$S, "Delivered") -> 24 | F2: =COUNTIFS(Working_Data!$Y:$Y, A2, Working_Data!$T:$T, "Yes") -> 11
A3: =A2+7 -> 2024-10-07 | B3: =COUNTIF(Working_Data!Y:Y, A3) -> 29 | C3: =COUNTIFS(Working_Data!Y:Y, A2, Working_Data!S:S, "*Delivered*") -> 24 | D3: =AVERAGEIF(Working_Data!$Y:$Y, A3, Working_Data!$L:$L) -> 5.1724138 | E3: =COUNTIFS(Working_Data!$Y:$Y, A3, Working_Data!$S:$S, "Delivered") -> 27 | F3: =COUNTIFS(Working_Data!$Y:$Y, A3, Working_Data!$T:$T, "Yes") -> 11
A4: =A3+7 -> 2024-10-14 | B4: =COUNTIF(Working_Data!Y:Y, A4) -> 28 | C4: =COUNTIFS(Working_Data!Y:Y, A3, Working_Data!S:S, "*Delivered*") -> 27 | D4: =AVERAGEIF(Working_Data!$Y:$Y, A4, Working_Data!$L:$L) -> 5.1785714 | E4: =COUNTIFS(Working_Data!$Y:$Y, A4, Working_Data!$S:$S, "Delivered") -> 26 | F4: =COUNTIFS(Working_Data!$Y:$Y, A4, Working_Data!$T:$T, "Yes") -> 13
A5: =A4+7 -> 2024-10-21 | B5: =COUNTIF(Working_Data!Y:Y, A5) -> 27 | C5: =COUNTIFS(Working_Data!Y:Y, A4, Working_Data!S:S, "*Delivered*") -> 26 | D5: =AVERAGEIF(Working_Data!$Y:$Y, A5, Working_Data!$L:$L) -> 5.5555556 | E5: =COUNTIFS(Working_Data!$Y:$Y, A5, Working_Data!$S:$S, "Delivered") -> 24 | F5: =COUNTIFS(Working_Data!$Y:$Y, A5, Working_Data!$T:$T, "Yes") -> 10
A6: =A5+7 -> 2024-10-28 | B6: =COUNTIF(Working_Data!Y:Y, A6) -> 33 | C6: =COUNTIFS(Working_Data!Y:Y, A5, Working_Data!S:S, "*Delivered*") -> 24 | D6: =AVERAGEIF(Working_Data!$Y:$Y, A6, Working_Data!$L:$L) -> 40 | E6: =COUNTIFS(Working_Data!$Y:$Y, A6, Working_Data!$S:$S, "Delivered") -> 31 | F6: =COUNTIFS(Working_Data!$Y:$Y, A6, Working_Data!$T:$T, "Yes") -> 24
A7: =A6+7 -> 2024-11-04 | B7: =COUNTIF(Working_Data!Y:Y, A7) -> 21 | C7: =COUNTIFS(Working_Data!Y:Y, A6, Working_Data!S:S, "*Delivered*") -> 31 | D7: =AVERAGEIF(Working_Data!$Y:$Y, A7, Working_Data!$L:$L) -> 16.190476 | E7: =COUNTIFS(Working_Data!$Y:$Y, A7, Working_Data!$S:$S, "Delivered") -> 20 | F7: =COUNTIFS(Working_Data!$Y:$Y, A7, Working_Data!$T:$T, "Yes") -> 11
A8: =A7+7 -> 2024-11-11 | B8: =COUNTIF(Working_Data!Y:Y, A8) -> 21 | C8: =COUNTIFS(Working_Data!Y:Y, A7, Working_Data!S:S, "*Delivered*") -> 20 | D8: =AVERAGEIF(Working_Data!$Y:$Y, A8, Working_Data!$L:$L) -> 4.2857143 | E8: =COUNTIFS(Working_Data!$Y:$Y, A8, Working_Data!$S:$S, "Delivered") -> 20 | F8: =COUNTIFS(Working_Data!$Y:$Y, A8, Working_Data!$T:$T, "Yes") -> 12
A9: =A8+7 -> 2024-11-18 | B9: =COUNTIF(Working_Data!Y:Y, A9) -> 21 | C9: =COUNTIFS(Working_Data!Y:Y, A8, Working_Data!S:S, "*Delivered*") -> 20 | D9: =AVERAGEIF(Working_Data!$Y:$Y, A9, Working_Data!$L:$L) -> 3.5714286 | E9: =COUNTIFS(Working_Data!$Y:$Y, A9, Working_Data!$S:$S, "Delivered") -> 20 | F9: =COUNTIFS(Working_Data!$Y:$Y, A9, Working_Data!$T:$T, "Yes") -> 11
A10: =A9+7 -> 2024-11-25 | B10: =COUNTIF(Working_Data!Y:Y, A10) -> 22 | C10: =COUNTIFS(Working_Data!Y:Y, A9, Working_Data!S:S, "*Delivered*") -> 20 | D10: =AVERAGEIF(Working_Data!$Y:$Y, A10, Working_Data!$L:$L) -> 5.4545455 | E10: =COUNTIFS(Working_Data!$Y:$Y, A10, Working_Data!$S:$S, "Delivered") -> 21 | F10: =COUNTIFS(Working_Data!$Y:$Y, A10, Working_Data!$T:$T, "Yes") -> 13
A11: =A10+7 -> 2024-12-02 | B11: =COUNTIF(Working_Data!Y:Y, A11) -> 28 | C11: =COUNTIFS(Working_Data!Y:Y, A10, Working_Data!S:S, "*Delivered*") -> 21 | D11: =AVERAGEIF(Working_Data!$Y:$Y, A11, Working_Data!$L:$L) -> 8.5714286 | E11: =COUNTIFS(Working_Data!$Y:$Y, A11, Working_Data!$S:$S, "Delivered") -> 27 | F11: =COUNTIFS(Working_Data!$Y:$Y, A11, Working_Data!$T:$T, "Yes") -> 11
A12: =A11+7 -> 2024-12-09 | B12: =COUNTIF(Working_Data!Y:Y, A12) -> 28 | C12: =COUNTIFS(Working_Data!Y:Y, A11, Working_Data!S:S, "*Delivered*") -> 27 | D12: =AVERAGEIF(Working_Data!$Y:$Y, A12, Working_Data!$L:$L) -> 6.4285714 | E12: =COUNTIFS(Working_Data!$Y:$Y, A12, Working_Data!$S:$S, "Delivered") -> 27 | F12: =COUNTIFS(Working_Data!$Y:$Y, A12, Working_Data!$T:$T, "Yes") -> 16
A13: =A12+7 -> 2024-12-16 | B13: =COUNTIF(Working_Data!Y:Y, A13) -> 28 | C13: =COUNTIFS(Working_Data!Y:Y, A12, Working_Data!S:S, "*Delivered*") -> 27 | D13: =AVERAGEIF(Working_Data!$Y:$Y, A13, Working_Data!$L:$L) -> 7.1428571 | E13: =COUNTIFS(Working_Data!$Y:$Y, A13, Working_Data!$S:$S, "Delivered") -> 28 | F13: =COUNTIFS(Working_Data!$Y:$Y, A13, Working_Data!$T:$T, "Yes") -> 17
A14: =A13+7 -> 2024-12-23 | B14: =COUNTIF(Working_Data!Y:Y, A14) -> 28 | C14: =COUNTIFS(Working_Data!Y:Y, A13, Working_Data!S:S, "*Delivered*") -> 28 | D14: =AVERAGEIF(Working_Data!$Y:$Y, A14, Working_Data!$L:$L) -> 6.4285714 | E14: =COUNTIFS(Working_Data!$Y:$Y, A14, Working_Data!$S:$S, "Delivered") -> 28 | F14: =COUNTIFS(Working_Data!$Y:$Y, A14, Working_Data!$T:$T, "Yes") -> 17
A15: =A14+7 -> 2024-12-30 | B15: =COUNTIF(Working_Data!Y:Y, A15) -> 5 | C15: =COUNTIFS(Working_Data!Y:Y, A14, Working_Data!S:S, "*Delivered*") -> 28 | D15: =AVERAGEIF(Working_Data!$Y:$Y, A15, Working_Data!$L:$L) -> 8 | E15: =COUNTIFS(Working_Data!$Y:$Y, A15, Working_Data!$S:$S, "Delivered") -> 5 | F15: =COUNTIFS(Working_Data!$Y:$Y, A15, Working_Data!$T:$T, "Yes") -> 3
A16: =A15+7 -> 2025-01-06 | B16: =COUNTIF(Working_Data!Y:Y, A16) -> 0 | C16: =COUNTIFS(Working_Data!Y:Y, A15, Working_Data!S:S, "*Delivered*") -> 5 | D16: 0 | E16: =COUNTIFS(Working_Data!$Y:$Y, A16, Working_Data!$S:$S, "Delivered") -> 0 | F16: =COUNTIFS(Working_Data!$Y:$Y, A16, Working_Data!$T:$T, "Yes") -> 0
A21: Discount Category | B21: Total Orders | C21: Returns | D21: Return Rate
A22: No Discount | B22: =COUNTIF(Working_Data!AA:AA, "No Discount") -> 206 | C22: =COUNTIFS(Working_Data!AA:AA, "No Discount", Working_Data!T:T, "Yes") -> 103 | D22: =C22/B22 -> 0.5
A23: Low (1-20%) | B23: =COUNTIF(Working_Data!AA:AA, "Low (1-20%)") -> 100 | C23: =COUNTIFS(Working_Data!AA:AA, "Low (1-20%)", Working_Data!T:T, "Yes") -> 48 | D23: =C23/B23 -> 0.48
A24: High (20%+) | B24: =COUNTIF(Working_Data!AA:AA, "High (20%+)") -> 40 | C24: =COUNTIFS(Working_Data!AA:AA, "High (20%+)", Working_Data!T:T, "Yes") -> 29 | D24: =C24/B24 -> 0.725

Sheet Descriptive_Analysis
A1: Order ID | B1: Qty | C1: Total | D1: Return_Rate | E1: Return | F1: Net_Revenue | G1: AOV | N1: SKU | O1: Total (Rs)
A2: =COUNTA(Working_Data!A2:A347) -> 346 | B2: =SUM(Working_Data!I:I) -> 409 | C2: =SUM(Working_Data!J:J) -> 1023789 | D2: =COUNTIF(Working_Data!T:T, "Yes") / COUNTIF(Working_Data!S:S, "Delivered") -> 0.54878049 | E2: =COUNTIF(Working_Data!U2:U347,"<>") -> 180 | F2: =SUMPRODUCT(Working_Data!J2:J347*(1- VALUE(SUBSTITUTE(Working_Data!L2:L347,"%",""))/100)) -> 909607.35 | G2: =F2/A2 -> 2628.923 | N2: TOP-CAS-M | O2: =SUMIF(Working_Data!E:E, N2, Working_Data!J:J) -> 2598
N3: DRS-FRM-S | O3: =SUMIF(Working_Data!E:E, N3, Working_Data!J:J) -> 2499
E4: Month | F4: Orders | N4: BOT-JNS-L | O4: =SUMIF(Working_Data!E:E, N4, Working_Data!J:J) -> 1899
E5: Oct | F5: =COUNTIFS(Working_Data!B:B,">="&DATE(2024,10,1),Working_Data!B:B,"<="&DATE(2024,10,31)) -> 132 | N5: OUT-JKT-XL | O5: =SUMIF(Working_Data!E:E, N5, Working_Data!J:J) -> 3499
E6: Nov | F6: =COUNTIFS(Working_Data!B:B,">="&DATE(2024,11,1),Working_Data!B:B,"<="&DATE(2024,11,30)) -> 93 | N6: ACC-SCF-OS | O6: =SUMIF(Working_Data!E:E, N6, Working_Data!J:J) -> 2397
E7: Dec | F7: =COUNTIFS(Working_Data!B:B,">="&DATE(2024,12,1),Working_Data!B:B,"<="&DATE(2024,12,31)) -> 121 | N7: TOP-FRM-S | O7: =SUMIF(Working_Data!E:E, N7, Working_Data!J:J) -> 3198
N8: DRS-CAS-M | O8: =SUMIF(Working_Data!E:E, N8, Working_Data!J:J) -> 2199
F9: Reason | G9: Count | N9: BOT-TRS-L | O9: =SUMIF(Working_Data!E:E, N9, Working_Data!J:J) -> 2299
E10: 1 | F10: Size Issue | G10: =COUNTIF(Working_Data!U2:U347, "Size Issue") -> 67 | N10: TOP-CAS-XL | O10: =SUMIF(Working_Data!E:E, N10, Working_Data!J:J) -> 6995
E11: 2 | F11: Quality Defect | G11: =COUNTIF(Working_Data!U2:U347, "Quality Defect") -> 32 | N11: OUT-BLZ-M | O11: =SUMIF(Working_Data!E:E, N11, Working_Data!J:J) -> 4999
E12: 3 | F12: Changed Mind | G12: =COUNTIF(Working_Data!U2:U347, "Changed Mind") -> 29 | N12: ACC-BAG-OS | O12: =SUMIF(Working_Data!E:E, N12, Working_Data!J:J) -> 2598
E13: 4 | F13: Wrong Item | G13: =COUNTIF(Working_Data!U2:U347, "Wrong Item") -> 28 | N13: DRS-PRT-S | O13: =SUMIF(Working_Data!E:E, N13, Working_Data!J:J) -> 3299
E14: 5 | F14: Damaged in Transit | G14: =COUNTIF(Working_Data!U2:U347, "Damaged in Transit") -> 24 | N14: TOP-SLK-M | O14: =SUMIF(Working_Data!E:E, N14, Working_Data!J:J) -> 2499
N15: BOT-SKT-S | O15: =SUMIF(Working_Data!E:E, N15, Working_Data!J:J) -> 3598
N16: OUT-CRD-L | O16: =SUMIF(Working_Data!E:E, N16, Working_Data!J:J) -> 2799
N17: ACC-JWL-OS | O17: =SUMIF(Working_Data!E:E, N17, Working_Data!J:J) -> 2396
E18: Top 5 SKUs | F18: Top 5 SKUs Total | N18: TOP-CRP-XS | O18: =SUMIF(Working_Data!E:E, N18, Working_Data!J:J) -> 999
E19: {=INDEX($N$2:$N$337, SMALL(IF($O$2:$O$337=F19, ROW($O$2:$O$337)-ROW($O$2)+1), COUNTIF($F$19:F19, F19)))} -> OUT-CPE-M | F19: =LARGE($O$2:$O$337, 1) -> 10598 | N19: DRS-MAX-M | O19: =SUMIF(Working_Data!E:E, N19, Working_Data!J:J) -> 2899
E20: {=INDEX($N$2:$N$337, SMALL(IF($O$2:$O$337=F20, ROW($O$2:$O$337)-ROW($O$2)+1), COUNTIF($F$19:F20, F20)))} -> OUT-VLV-L | F20: =LARGE($O$2:$O$337, 2) -> 10498 | N20: BOT-JGR-M | O20: =SUMIF(Working_Data!E:E, N20, Working_Data!J:J) -> 2998
E21: {=INDEX($N$2:$N$337, SMALL(IF($O$2:$O$337=F21, ROW($O$2:$O$337)-ROW($O$2)+1), COUNTIF($F$19:F21, F21)))} -> DRS-EVE-S | F21: =LARGE($O$2:$O$337, 3) -> 10098 | N21: OUT-VST-S | O21: =SUMIF(Working_Data!E:E, N21, Working_Data!J:J) -> 3999
E22: {=INDEX($N$2:$N$337, SMALL(IF($O$2:$O$337=F22, ROW($O$2:$O$337)-ROW($O$2)+1), COUNTIF($F$19:F22, F22)))} -> DRS-LHG-M | F22: =LARGE($O$2:$O$337, 4) -> 8999 | N22: TOP-TUN-L | O22: =SUMIF(Working_Data!E:E, N22, Working_Data!J:J) -> 1699
E23: {=INDEX($N$2:$N$337, SMALL(IF($O$2:$O$337=F23, ROW($O$2:$O$337)-ROW($O$2)+1), COUNTIF($F$19:F23, F23)))} -> OUT-FUR-L | F23: =LARGE($O$2:$O$337, 5) -> 8999 | N23: DRS-SHT-XS | O23: =SUMIF(Working_Data!E:E, N23, Working_Data!J:J) -> 2399
N24: ACC-BLT-M | O24: =SUMIF(Working_Data!E:E, N24, Working_Data!J:J) -> 899
N25: BOT-SHT-M | O25: =SUMIF(Working_Data!E:E, N25, Working_Data!J:J) -> 3597
N26: TOP-PLO-L | O26: =SUMIF(Working_Data!E:E, N26, Working_Data!J:J) -> 3598
N27: DRS-WRK-M | O27: =SUMIF(Working_Data!E:E, N27, Working_Data!J:J) -> 2699
N28: OUT-TRN-L | O28: =SUMIF(Working_Data!E:E, N28, Working_Data!J:J) -> 4599
N29: ACC-HAT-OS | O29: =SUMIF(Working_Data!E:E, N29, Working_Data!J:J) -> 1099
N30: TOP-DNM-M | O30: =SUMIF(Working_Data!E:E, N30, Working_Data!J:J) -> 1899
N31: BOT-CRG-L | O31: =SUMIF(Working_Data!E:E, N31, Working_Data!J:J) -> 2199
N32: DRS-EVE-S | O32: =SUMIF(Working_Data!E:E, N32, Working_Data!J:J) -> 10098
N33: TOP-BAS-M | O33: =SUMIF(Working_Data!E:E, N33, Working_Data!J:J) -> 1798
N34: OUT-WOL-L | O34: =SUMIF(Working_Data!E:E, N34, Working_Data!J:J) -> 6999
N35: ACC-WCH-OS | O35: =SUMIF(Working_Data!E:E, N35, Working_Data!J:J) -> 2999
... N337: DRS-CNT-S | O337: =SUMIF(Working_Data!E:E, N337, Working_Data!J:J) -> 4499

Sheet VALIDATION_SUMMARY
A1: Check Name | B1: Formula Used | C1: Result | D1: Pass/Fail
A2: Order ID missing | B2: COUNTBLANK(Working_Data!A2:A347) | C2: =COUNTBLANK(Working_Data!A2:A347) -> 0 | D2: =IF(C2=0, "Pass", "Fail") -> Pass
A3: Duplicate order_id | B3: COUNTIF(Working_Data!A:A, Working_Data!A2)-1 | C3: =COUNTIF(Working_Data!A:A, Working_Data!A2)-1 -> 0 | D3: =IF(C3=0, "Pass", "Fail") -> Pass
A4: Delivered without delivery_date | B4: COUNTIFS( Working_Data!P:P,"Delivered", Working_Data!O:O,"" ) | C4: =COUNTIFS( Working_Data!P:P,"Delivered", Working_Data!O:O,"" ) -> 0 | D4: =IF(C4=0, "Pass", "Fail") -> Pass
A5: Return Yes without reason | B5: COUNTIFS( Working_Data!Q:Q,"Yes", Working_Data!R:R,"" ) | C5: =COUNTIFS( Working_Data!Q:Q,"Yes", Working_Data!R:R,"" ) -> 0 | D5: Pass
A6: Return before delivery | B6: COUNTIFS( Working_Data!S:S,"<"&Working_Data!O:O ) | C6: =SUMPRODUCT(--(Working_Data!V2:V347 < Working_Data!R2:R347) * (Working_Data!V2:V347 <> "")) -> 0 | D6: =IF(C5=0, "Pass", "Fail") -> Pass

Sheet Final_KPIs
A1: Total Orders | B1: Delivered Orders | C1: GMV | D1: Net Revenue | E1: Average Order Value (AOV) | F1: Average Discount %
A2: =COUNTA(Working_Data!A2:A347) -> 346 | B2: =COUNTIF(Working_Data!S:S, "Delivered") -> 328 | C2: =SUM(Working_Data!J:J) -> 1023789 | D2: =SUMPRODUCT(Working_Data!J2:J347, 1-(Working_Data!L2:L347/100)) -> 909607.35 | E2: =AVERAGE(Working_Data!J2:J347) -> 2958.9277 | F2: =AVERAGE(Working_Data!L2:L347) -> 9.7398844

Sheet Cleaning_Log
A1: Issue Type | B1: Column Name | C1: What I Observed | D1: Why It’s a Problem | E1: Action Taken
A2: Missing Value Check | B2: Order ID, Order Date, Customer ID, Unit Price, Qty, Total | C2: No missing values found in critical columns | D2: Critical fields must be present to ensure accurate order, revenue, and fulfillment analysis | E2: No action required
A3: Date logic checks performed (1 violations found) | B3: Order Date, Del Date, Ret Rec | C3: No cases where Del Date occurs before Order Date or Ret Rec occurs before Del Date. B4 is 10/1 while others are 1/10 | D3: Incorrect date order breaks delivery time calculations, return window validation, and leads to inaccurate operational KPIs. | E3: No action required
A4: Corrected mistaken spelling | B4: Status | C4: Delivered was miswritten as delievered | D4: Incorrect spelling leads to miscalculations. | E4: Action taken
A5: Feature Engineering | B5: Added columns weekstart,DeliverDays and DiscountTrap | C5: Raw data was transactional only (row-level) | D5: We could not analyze weekly trends or identify the "Discount Trap" impact without aggregating metrics. | E5: Engineered calculated columns to group sales by week and flag high-risk discount orders.

Sheet Insights_Summary
A1: Key_Insights
A3: Key insights
A4: Weekly orders peak during the Diwali week (28-10-2024), coinciding with the highest discount levels.
A5: Deep discounting during Diwali was counter-productive. While order volume peaked at 33 units, the 73% return rate meant Net Sales actually dropped by ~50% compared to the previous week. We effectively paid to ship inventory back and forth.
A8: Business conclusions
A9: Festive discounts effectively drive short-term demand but increase return-related operational costs.
A10: Promotional effects extend beyond the sale week due to the 30-day return window.
A11: Discount intensity should be optimized to balance GMV growth and net revenue quality.
A14: Business recommendations
A15: Introduce discount caps during peak festive periods to control return rates.
A16: Focus deeper promotions on lower-risk customers rather than blanket discounting.
A17: Improve size guidance and post-purchase communication during high-volume weeks to reduce preventable returns.
... A23: Return rate is calculated using delivered orders only.
